{
"meta":{"test_sets":[],"test_metrics":[],"learn_metrics":[{"best_value":"Min","name":"RMSE"}],"launch_mode":"Train","parameters":"","iteration_count":1000,"learn_sets":["learn"],"name":"experiment"},
"iterations":[
{"learn":[14.59871775],"iteration":0,"passed_time":0.1664771546,"remaining_time":166.3106775},
{"learn":[14.22518863],"iteration":1,"passed_time":0.1684837153,"remaining_time":84.07337392},
{"learn":[13.8866124],"iteration":2,"passed_time":0.1701620849,"remaining_time":56.55053288},
{"learn":[13.52356875],"iteration":3,"passed_time":0.1718302928,"remaining_time":42.7857429},
{"learn":[13.18870211],"iteration":4,"passed_time":0.1741387186,"remaining_time":34.65360501},
{"learn":[12.9124226],"iteration":5,"passed_time":0.1765693506,"remaining_time":29.25165575},
{"learn":[12.60003351],"iteration":6,"passed_time":0.178919503,"remaining_time":25.38100949},
{"learn":[12.32990573],"iteration":7,"passed_time":0.1807681885,"remaining_time":22.41525537},
{"learn":[12.0660619],"iteration":8,"passed_time":0.1825766109,"remaining_time":20.10371348},
{"learn":[11.77309809],"iteration":9,"passed_time":0.1842614388,"remaining_time":18.24188244},
{"learn":[11.49227636],"iteration":10,"passed_time":0.1860081096,"remaining_time":16.72382003},
{"learn":[11.26264833],"iteration":11,"passed_time":0.1882038707,"remaining_time":15.49545202},
{"learn":[11.04260393],"iteration":12,"passed_time":0.1899800537,"remaining_time":14.42387023},
{"learn":[10.79916926],"iteration":13,"passed_time":0.1918187723,"remaining_time":13.50952211},
{"learn":[10.5541002],"iteration":14,"passed_time":0.1934465877,"remaining_time":12.70299259},
{"learn":[10.31918115],"iteration":15,"passed_time":0.1955119442,"remaining_time":12.02398457},
{"learn":[10.10004441],"iteration":16,"passed_time":0.1971040761,"remaining_time":11.39725334},
{"learn":[9.894556723],"iteration":17,"passed_time":0.1987678517,"remaining_time":10.84389058},
{"learn":[9.690174082],"iteration":18,"passed_time":0.2006151913,"remaining_time":10.35807909},
{"learn":[9.506034866],"iteration":19,"passed_time":0.2026645536,"remaining_time":9.930563125},
{"learn":[9.338524633],"iteration":20,"passed_time":0.204367879,"remaining_time":9.527435882},
{"learn":[9.170203312],"iteration":21,"passed_time":0.2059505498,"remaining_time":9.155438076},
{"learn":[9.010299969],"iteration":22,"passed_time":0.2074989056,"remaining_time":8.814192643},
{"learn":[8.843866678],"iteration":23,"passed_time":0.2090128543,"remaining_time":8.499856074},
{"learn":[8.690548059],"iteration":24,"passed_time":0.2106201216,"remaining_time":8.214184743},
{"learn":[8.555307687],"iteration":25,"passed_time":0.2122038099,"remaining_time":7.949481187},
{"learn":[8.413851302],"iteration":26,"passed_time":0.2138418242,"remaining_time":7.70622574},
{"learn":[8.29256019],"iteration":27,"passed_time":0.2155405998,"remaining_time":7.482337966},
{"learn":[8.162193833],"iteration":28,"passed_time":0.2172850615,"remaining_time":7.275303266},
{"learn":[8.040736294],"iteration":29,"passed_time":0.2188221303,"remaining_time":7.075248879},
{"learn":[7.921220278],"iteration":30,"passed_time":0.2203915028,"remaining_time":6.889011813},
{"learn":[7.809589039],"iteration":31,"passed_time":0.2218946099,"remaining_time":6.71231195},
{"learn":[7.699675801],"iteration":32,"passed_time":0.2234087616,"remaining_time":6.546553712},
{"learn":[7.60645267],"iteration":33,"passed_time":0.224866385,"remaining_time":6.38885082},
{"learn":[7.498880302],"iteration":34,"passed_time":0.2263880304,"remaining_time":6.241841411},
{"learn":[7.401158744],"iteration":35,"passed_time":0.2282964262,"remaining_time":6.113270969},
{"learn":[7.306431077],"iteration":36,"passed_time":0.23001839,"remaining_time":5.986694853},
{"learn":[7.223863468],"iteration":37,"passed_time":0.231695725,"remaining_time":5.865560196},
{"learn":[7.143477682],"iteration":38,"passed_time":0.2330605414,"remaining_time":5.742850777},
{"learn":[7.062817131],"iteration":39,"passed_time":0.2344185871,"remaining_time":5.62604609},
{"learn":[6.990793435],"iteration":40,"passed_time":0.2357826887,"remaining_time":5.515014597},
{"learn":[6.931862224],"iteration":41,"passed_time":0.2370849907,"remaining_time":5.407795741},
{"learn":[6.858296558],"iteration":42,"passed_time":0.2382414361,"remaining_time":5.302257079},
{"learn":[6.786268161],"iteration":43,"passed_time":0.2394520603,"remaining_time":5.202640219},
{"learn":[6.717118549],"iteration":44,"passed_time":0.2406812934,"remaining_time":5.107791894},
{"learn":[6.652948106],"iteration":45,"passed_time":0.2418738121,"remaining_time":5.016252538},
{"learn":[6.589686076],"iteration":46,"passed_time":0.2430792081,"remaining_time":4.928818837},
{"learn":[6.531283097],"iteration":47,"passed_time":0.2443383693,"remaining_time":4.846044325},
{"learn":[6.471368031],"iteration":48,"passed_time":0.2455420862,"remaining_time":4.765520898},
{"learn":[6.416481395],"iteration":49,"passed_time":0.2466985986,"remaining_time":4.687273373},
{"learn":[6.369870822],"iteration":50,"passed_time":0.2477875261,"remaining_time":4.610791417},
{"learn":[6.325678067],"iteration":51,"passed_time":0.2488493081,"remaining_time":4.536714309},
{"learn":[6.275766122],"iteration":52,"passed_time":0.2498713558,"remaining_time":4.464682528},
{"learn":[6.224773967],"iteration":53,"passed_time":0.2509104922,"remaining_time":4.395580105},
{"learn":[6.182249254],"iteration":54,"passed_time":0.2521320249,"remaining_time":4.332086609},
{"learn":[6.139904173],"iteration":55,"passed_time":0.2531606619,"remaining_time":4.267565443},
{"learn":[6.100525536],"iteration":56,"passed_time":0.2542013179,"remaining_time":4.205470926},
{"learn":[6.062568564],"iteration":57,"passed_time":0.2551403917,"remaining_time":4.143831878},
{"learn":[6.030559288],"iteration":58,"passed_time":0.2563234672,"remaining_time":4.088142078},
{"learn":[5.997931376],"iteration":59,"passed_time":0.2575616102,"remaining_time":4.035131893},
{"learn":[5.964103835],"iteration":60,"passed_time":0.2589889031,"remaining_time":3.98673082},
{"learn":[5.933729724],"iteration":61,"passed_time":0.2602641905,"remaining_time":3.937545334},
{"learn":[5.901932711],"iteration":62,"passed_time":0.2613809352,"remaining_time":3.887522798},
{"learn":[5.873727795],"iteration":63,"passed_time":0.2624724399,"remaining_time":3.838659434},
{"learn":[5.846485734],"iteration":64,"passed_time":0.2636052699,"remaining_time":3.791860421},
{"learn":[5.820630862],"iteration":65,"passed_time":0.2647244992,"remaining_time":3.746252761},
{"learn":[5.793646238],"iteration":66,"passed_time":0.2657730721,"remaining_time":3.700989198},
{"learn":[5.765388646],"iteration":67,"passed_time":0.2668371822,"remaining_time":3.657239026},
{"learn":[5.747073912],"iteration":68,"passed_time":0.2679057654,"remaining_time":3.614786487},
{"learn":[5.722315217],"iteration":69,"passed_time":0.2689221023,"remaining_time":3.572822216},
{"learn":[5.699970599],"iteration":70,"passed_time":0.2698944631,"remaining_time":3.531436003},
{"learn":[5.682732647],"iteration":71,"passed_time":0.2709487692,"remaining_time":3.492228581},
{"learn":[5.663525791],"iteration":72,"passed_time":0.2719882284,"remaining_time":3.453877915},
{"learn":[5.642381613],"iteration":73,"passed_time":0.2735539188,"remaining_time":3.423120659},
{"learn":[5.621404779],"iteration":74,"passed_time":0.2746350855,"remaining_time":3.387166055},
{"learn":[5.602460129],"iteration":75,"passed_time":0.2756767092,"remaining_time":3.351648412},
{"learn":[5.587337574],"iteration":76,"passed_time":0.2766033802,"remaining_time":3.315648311},
{"learn":[5.572393026],"iteration":77,"passed_time":0.2776498266,"remaining_time":3.281963335},
{"learn":[5.558425806],"iteration":78,"passed_time":0.2786986837,"remaining_time":3.249132756},
{"learn":[5.541518902],"iteration":79,"passed_time":0.2797020377,"remaining_time":3.216573433},
{"learn":[5.526157283],"iteration":80,"passed_time":0.2809303946,"remaining_time":3.187346082},
{"learn":[5.511746977],"iteration":81,"passed_time":0.2820780276,"remaining_time":3.157897918},
{"learn":[5.504975022],"iteration":82,"passed_time":0.2826170367,"remaining_time":3.122407502},
{"learn":[5.493980522],"iteration":83,"passed_time":0.2836802832,"remaining_time":3.093465946},
{"learn":[5.480745463],"iteration":84,"passed_time":0.2847218623,"remaining_time":3.064947105},
{"learn":[5.464052013],"iteration":85,"passed_time":0.2857967068,"remaining_time":3.037420814},
{"learn":[5.449143727],"iteration":86,"passed_time":0.2869656241,"remaining_time":3.011489826},
{"learn":[5.438255432],"iteration":87,"passed_time":0.2882744351,"remaining_time":2.987571418},
{"learn":[5.425927931],"iteration":88,"passed_time":0.289297124,"remaining_time":2.961232359},
{"learn":[5.412331217],"iteration":89,"passed_time":0.290317818,"remaining_time":2.935435715},
{"learn":[5.400691499],"iteration":90,"passed_time":0.2913413987,"remaining_time":2.910212433},
{"learn":[5.391618744],"iteration":91,"passed_time":0.2923541899,"remaining_time":2.885408744},
{"learn":[5.380766572],"iteration":92,"passed_time":0.2932765261,"remaining_time":2.860234507},
{"learn":[5.372207183],"iteration":93,"passed_time":0.2943270958,"remaining_time":2.836812221},
{"learn":[5.362918837],"iteration":94,"passed_time":0.2954122634,"remaining_time":2.814190509},
{"learn":[5.348292324],"iteration":95,"passed_time":0.2963665262,"remaining_time":2.790784788},
{"learn":[5.339772295],"iteration":96,"passed_time":0.2973975039,"remaining_time":2.768556145},
{"learn":[5.331515983],"iteration":97,"passed_time":0.2983312268,"remaining_time":2.745864965},
{"learn":[5.323861644],"iteration":98,"passed_time":0.2993645966,"remaining_time":2.724520218},
{"learn":[5.313277281],"iteration":99,"passed_time":0.3004529105,"remaining_time":2.704076194},
{"learn":[5.30685627],"iteration":100,"passed_time":0.3014230079,"remaining_time":2.682963209},
{"learn":[5.29652059],"iteration":101,"passed_time":0.3028905345,"remaining_time":2.66662451},
{"learn":[5.288350766],"iteration":102,"passed_time":0.3040023292,"remaining_time":2.647476595},
{"learn":[5.27993346],"iteration":103,"passed_time":0.3050287103,"remaining_time":2.627939658},
{"learn":[5.271789139],"iteration":104,"passed_time":0.3060170754,"remaining_time":2.608431261},
{"learn":[5.262684686],"iteration":105,"passed_time":0.3071340647,"remaining_time":2.590357112},
{"learn":[5.251619772],"iteration":106,"passed_time":0.3081250226,"remaining_time":2.571548086},
{"learn":[5.241012171],"iteration":107,"passed_time":0.3090759205,"remaining_time":2.552738158},
{"learn":[5.232684032],"iteration":108,"passed_time":0.3101879885,"remaining_time":2.535573374},
{"learn":[5.224267141],"iteration":109,"passed_time":0.3111784868,"remaining_time":2.517716847},
{"learn":[5.216324968],"iteration":110,"passed_time":0.3122694712,"remaining_time":2.500969008},
{"learn":[5.211102527],"iteration":111,"passed_time":0.3133679981,"remaining_time":2.484560557},
{"learn":[5.206364257],"iteration":112,"passed_time":0.3143464082,"remaining_time":2.467480213},
{"learn":[5.196937641],"iteration":113,"passed_time":0.3153709454,"remaining_time":2.451040857},
{"learn":[5.190746047],"iteration":114,"passed_time":0.3164429977,"remaining_time":2.435235243},
{"learn":[5.181885213],"iteration":115,"passed_time":0.3180070127,"remaining_time":2.423432752},
{"learn":[5.178293568],"iteration":116,"passed_time":0.31893008,"remaining_time":2.40696804},
{"learn":[5.170991438],"iteration":117,"passed_time":0.320041067,"remaining_time":2.392171365},
{"learn":[5.166257212],"iteration":118,"passed_time":0.3209599675,"remaining_time":2.376182617},
{"learn":[5.161421246],"iteration":119,"passed_time":0.3219040158,"remaining_time":2.360629449},
{"learn":[5.158223542],"iteration":120,"passed_time":0.3228900252,"remaining_time":2.34562258},
{"learn":[5.15470988],"iteration":121,"passed_time":0.3240799726,"remaining_time":2.332313246},
{"learn":[5.146388143],"iteration":122,"passed_time":0.3252135456,"remaining_time":2.318799021},
{"learn":[5.139529364],"iteration":123,"passed_time":0.3262241159,"remaining_time":2.304615528},
{"learn":[5.134276023],"iteration":124,"passed_time":0.3272100108,"remaining_time":2.290470075},
{"learn":[5.128536065],"iteration":125,"passed_time":0.328199159,"remaining_time":2.276556071},
{"learn":[5.123300353],"iteration":126,"passed_time":0.328989886,"remaining_time":2.261481657},
{"learn":[5.116200518],"iteration":127,"passed_time":0.3300189514,"remaining_time":2.248254107},
{"learn":[5.108728704],"iteration":128,"passed_time":0.3311167346,"remaining_time":2.235679657},
{"learn":[5.104075866],"iteration":129,"passed_time":0.3327427169,"remaining_time":2.226816644},
{"learn":[5.100317606],"iteration":130,"passed_time":0.3338198039,"remaining_time":2.214422974},
{"learn":[5.095814182],"iteration":131,"passed_time":0.3348903842,"remaining_time":2.202157981},
{"learn":[5.092146915],"iteration":132,"passed_time":0.3358599432,"remaining_time":2.189402787},
{"learn":[5.085258329],"iteration":133,"passed_time":0.3368642261,"remaining_time":2.177047909},
{"learn":[5.079219421],"iteration":134,"passed_time":0.3378901223,"remaining_time":2.164999672},
{"learn":[5.076476829],"iteration":135,"passed_time":0.3388899625,"remaining_time":2.152947997},
{"learn":[5.072133867],"iteration":136,"passed_time":0.3398752981,"remaining_time":2.140966294},
{"learn":[5.067031564],"iteration":137,"passed_time":0.3409094846,"remaining_time":2.129449099},
{"learn":[5.061358312],"iteration":138,"passed_time":0.341880119,"remaining_time":2.117689082},
{"learn":[5.056759124],"iteration":139,"passed_time":0.3428638948,"remaining_time":2.106163925},
{"learn":[5.050254],"iteration":140,"passed_time":0.3438921473,"remaining_time":2.095059252},
{"learn":[5.048376474],"iteration":141,"passed_time":0.3444967338,"remaining_time":2.081536603},
{"learn":[5.042603751],"iteration":142,"passed_time":0.3454433705,"remaining_time":2.070244535},
{"learn":[5.037477349],"iteration":143,"passed_time":0.3464047075,"remaining_time":2.059183539},
{"learn":[5.03230489],"iteration":144,"passed_time":0.3481347652,"remaining_time":2.05279465},
{"learn":[5.025976187],"iteration":145,"passed_time":0.3493394691,"remaining_time":2.043396621},
{"learn":[5.01952451],"iteration":146,"passed_time":0.3503325312,"remaining_time":2.032881967},
{"learn":[5.017569424],"iteration":147,"passed_time":0.3514076115,"remaining_time":2.022968142},
{"learn":[5.008962367],"iteration":148,"passed_time":0.3524286403,"remaining_time":2.012864247},
{"learn":[5.003880266],"iteration":149,"passed_time":0.3534751722,"remaining_time":2.003025976},
{"learn":[4.996387564],"iteration":150,"passed_time":0.3544768809,"remaining_time":1.993052132},
{"learn":[4.993361683],"iteration":151,"passed_time":0.3554933071,"remaining_time":1.98327845},
{"learn":[4.99005752],"iteration":152,"passed_time":0.3565146073,"remaining_time":1.973646225},
{"learn":[4.986908764],"iteration":153,"passed_time":0.3574407933,"remaining_time":1.963603319},
{"learn":[4.985207175],"iteration":154,"passed_time":0.3584273264,"remaining_time":1.954007037},
{"learn":[4.979003494],"iteration":155,"passed_time":0.3594286848,"remaining_time":1.944601346},
{"learn":[4.973142217],"iteration":156,"passed_time":0.3604282617,"remaining_time":1.935293151},
{"learn":[4.967056696],"iteration":157,"passed_time":0.361350014,"remaining_time":1.925675391},
{"learn":[4.961460696],"iteration":158,"passed_time":0.3627725422,"remaining_time":1.918815774},
{"learn":[4.954240363],"iteration":159,"passed_time":0.3640223078,"remaining_time":1.911117116},
{"learn":[4.952320707],"iteration":160,"passed_time":0.3647713027,"remaining_time":1.900888962},
{"learn":[4.948337777],"iteration":161,"passed_time":0.3660105027,"remaining_time":1.893313588},
{"learn":[4.943228639],"iteration":162,"passed_time":0.3671030986,"remaining_time":1.88506315},
{"learn":[4.938545759],"iteration":163,"passed_time":0.368347491,"remaining_time":1.877673795},
{"learn":[4.935330572],"iteration":164,"passed_time":0.3694580324,"remaining_time":1.869681558},
{"learn":[4.932051543],"iteration":165,"passed_time":0.370751761,"remaining_time":1.862692583},
{"learn":[4.928964153],"iteration":166,"passed_time":0.3717524232,"remaining_time":1.854309991},
{"learn":[4.922860227],"iteration":167,"passed_time":0.3729518428,"remaining_time":1.846999603},
{"learn":[4.917668772],"iteration":168,"passed_time":0.3741407036,"remaining_time":1.839709613},
{"learn":[4.910365386],"iteration":169,"passed_time":0.3753432962,"remaining_time":1.832558446},
{"learn":[4.906457206],"iteration":170,"passed_time":0.3771212565,"remaining_time":1.828266209},
{"learn":[4.901996508],"iteration":171,"passed_time":0.378389765,"remaining_time":1.821550729},
{"learn":[4.896816173],"iteration":172,"passed_time":0.3796192309,"remaining_time":1.814711584},
{"learn":[4.891123132],"iteration":173,"passed_time":0.3808329567,"remaining_time":1.807862197},
{"learn":[4.887630202],"iteration":174,"passed_time":0.3819817648,"remaining_time":1.800771177},
{"learn":[4.885259712],"iteration":175,"passed_time":0.3830356775,"remaining_time":1.793303399},
{"learn":[4.880659728],"iteration":176,"passed_time":0.3841229552,"remaining_time":1.786063233},
{"learn":[4.877299723],"iteration":177,"passed_time":0.3851581295,"remaining_time":1.778651587},
{"learn":[4.874038772],"iteration":178,"passed_time":0.3862149094,"remaining_time":1.771410283},
{"learn":[4.86943698],"iteration":179,"passed_time":0.3872112665,"remaining_time":1.763962436},
{"learn":[4.861268711],"iteration":180,"passed_time":0.3882593017,"remaining_time":1.756819713},
{"learn":[4.858673056],"iteration":181,"passed_time":0.3892676882,"remaining_time":1.749565763},
{"learn":[4.854036207],"iteration":182,"passed_time":0.3902212667,"remaining_time":1.742135382},
{"learn":[4.85130244],"iteration":183,"passed_time":0.3912963648,"remaining_time":1.735314314},
{"learn":[4.847510084],"iteration":184,"passed_time":0.393019615,"remaining_time":1.731410736},
{"learn":[4.845691673],"iteration":185,"passed_time":0.3941129599,"remaining_time":1.724773921},
{"learn":[4.842058646],"iteration":186,"passed_time":0.3951521238,"remaining_time":1.717960838},
{"learn":[4.838623675],"iteration":187,"passed_time":0.3961511288,"remaining_time":1.711035727},
{"learn":[4.834602161],"iteration":188,"passed_time":0.3971937194,"remaining_time":1.704360352},
{"learn":[4.830858976],"iteration":189,"passed_time":0.3981953731,"remaining_time":1.697569748},
{"learn":[4.827590511],"iteration":190,"passed_time":0.3991855403,"remaining_time":1.69079111},
{"learn":[4.822246226],"iteration":191,"passed_time":0.4002399223,"remaining_time":1.684343006},
{"learn":[4.816686395],"iteration":192,"passed_time":0.4012786384,"remaining_time":1.677885291},
{"learn":[4.814797121],"iteration":193,"passed_time":0.4022857099,"remaining_time":1.67135197},
{"learn":[4.811639392],"iteration":194,"passed_time":0.4032797166,"remaining_time":1.664821394},
{"learn":[4.804813432],"iteration":195,"passed_time":0.4043190546,"remaining_time":1.658533265},
{"learn":[4.80251613],"iteration":196,"passed_time":0.4053195844,"remaining_time":1.652140235},
{"learn":[4.800087884],"iteration":197,"passed_time":0.4063936747,"remaining_time":1.646099632},
{"learn":[4.794773135],"iteration":198,"passed_time":0.4080681721,"remaining_time":1.642525657},
{"learn":[4.791664833],"iteration":199,"passed_time":0.4092140251,"remaining_time":1.6368561},
{"learn":[4.785989873],"iteration":200,"passed_time":0.4102669098,"remaining_time":1.630861995},
{"learn":[4.782387142],"iteration":201,"passed_time":0.41124019,"remaining_time":1.624602335},
{"learn":[4.778623704],"iteration":202,"passed_time":0.4122202907,"remaining_time":1.618421535},
{"learn":[4.775772178],"iteration":203,"passed_time":0.4132040657,"remaining_time":1.61230606},
{"learn":[4.77023101],"iteration":204,"passed_time":0.4143131452,"remaining_time":1.606726588},
{"learn":[4.764496689],"iteration":205,"passed_time":0.4153289674,"remaining_time":1.600831069},
{"learn":[4.763138716],"iteration":206,"passed_time":0.4163460161,"remaining_time":1.594987395},
{"learn":[4.758053283],"iteration":207,"passed_time":0.4173557928,"remaining_time":1.589162442},
{"learn":[4.755063788],"iteration":208,"passed_time":0.4183483922,"remaining_time":1.583318556},
{"learn":[4.752465267],"iteration":209,"passed_time":0.419382543,"remaining_time":1.577677185},
{"learn":[4.748067377],"iteration":210,"passed_time":0.4203834595,"remaining_time":1.571955211},
{"learn":[4.744163298],"iteration":211,"passed_time":0.4216410249,"remaining_time":1.567231734},
{"learn":[4.736670896],"iteration":212,"passed_time":0.4230635925,"remaining_time":1.563150457},
{"learn":[4.73349255],"iteration":213,"passed_time":0.4240437847,"remaining_time":1.557469228},
{"learn":[4.731864595],"iteration":214,"passed_time":0.424967427,"remaining_time":1.551625257},
{"learn":[4.728398311],"iteration":215,"passed_time":0.4259146423,"remaining_time":1.545912405},
{"learn":[4.723865975],"iteration":216,"passed_time":0.4269780019,"remaining_time":1.54066256},
{"learn":[4.723483365],"iteration":217,"passed_time":0.4278315862,"remaining_time":1.534698626},
{"learn":[4.72095416],"iteration":218,"passed_time":0.428812816,"remaining_time":1.529236572},
{"learn":[4.716173382],"iteration":219,"passed_time":0.429804389,"remaining_time":1.523851925},
{"learn":[4.710563974],"iteration":220,"passed_time":0.4308202974,"remaining_time":1.518592813},
{"learn":[4.707160263],"iteration":221,"passed_time":0.4319496412,"remaining_time":1.513769463},
{"learn":[4.70408351],"iteration":222,"passed_time":0.4329151472,"remaining_time":1.508408383},
{"learn":[4.702501831],"iteration":223,"passed_time":0.4339263348,"remaining_time":1.503244803},
{"learn":[4.700269738],"iteration":224,"passed_time":0.434937187,"remaining_time":1.498116977},
{"learn":[4.695346302],"iteration":225,"passed_time":0.436028784,"remaining_time":1.493302119},
{"learn":[4.689769299],"iteration":226,"passed_time":0.4388959273,"remaining_time":1.494566307},
{"learn":[4.687919514],"iteration":227,"passed_time":0.440078381,"remaining_time":1.490089957},
{"learn":[4.682982074],"iteration":228,"passed_time":0.4411060466,"remaining_time":1.485121231},
{"learn":[4.679578702],"iteration":229,"passed_time":0.4421450521,"remaining_time":1.48022474},
{"learn":[4.675751423],"iteration":230,"passed_time":0.4431478311,"remaining_time":1.475241048},
{"learn":[4.672710726],"iteration":231,"passed_time":0.4441675701,"remaining_time":1.470347818},
{"learn":[4.6690533],"iteration":232,"passed_time":0.4452311424,"remaining_time":1.46563213},
{"learn":[4.667595702],"iteration":233,"passed_time":0.4462155036,"remaining_time":1.460688358},
{"learn":[4.664241291],"iteration":234,"passed_time":0.4472222031,"remaining_time":1.455851002},
{"learn":[4.662246999],"iteration":235,"passed_time":0.4482199883,"remaining_time":1.45101725},
{"learn":[4.658668443],"iteration":236,"passed_time":0.4493543033,"remaining_time":1.446655415},
{"learn":[4.658017572],"iteration":237,"passed_time":0.4503846979,"remaining_time":1.441987982},
{"learn":[4.657656705],"iteration":238,"passed_time":0.4513929363,"remaining_time":1.437280437},
{"learn":[4.653242871],"iteration":239,"passed_time":0.4529905451,"remaining_time":1.43447006},
{"learn":[4.6507302],"iteration":240,"passed_time":0.4541866816,"remaining_time":1.430405358},
{"learn":[4.647671336],"iteration":241,"passed_time":0.4553038279,"remaining_time":1.426116949},
{"learn":[4.645506007],"iteration":242,"passed_time":0.4562594601,"remaining_time":1.421351487},
{"learn":[4.641297906],"iteration":243,"passed_time":0.4572994355,"remaining_time":1.416878579},
{"learn":[4.63798107],"iteration":244,"passed_time":0.4582980604,"remaining_time":1.412306268},
{"learn":[4.635062318],"iteration":245,"passed_time":0.459293783,"remaining_time":1.407754116},
{"learn":[4.631606017],"iteration":246,"passed_time":0.4602888087,"remaining_time":1.403228636},
{"learn":[4.630215494],"iteration":247,"passed_time":0.4613058463,"remaining_time":1.398798373},
{"learn":[4.62729814],"iteration":248,"passed_time":0.4624415882,"remaining_time":1.394753545},
{"learn":[4.624691756],"iteration":249,"passed_time":0.4635539013,"remaining_time":1.390661704},
{"learn":[4.621840053],"iteration":250,"passed_time":0.4652803446,"remaining_time":1.388426208},
{"learn":[4.619602091],"iteration":251,"passed_time":0.4664779732,"remaining_time":1.384625095},
{"learn":[4.613584029],"iteration":252,"passed_time":0.468537328,"remaining_time":1.38338887},
{"learn":[4.6119388],"iteration":253,"passed_time":0.4697116215,"remaining_time":1.379546731},
{"learn":[4.60870702],"iteration":254,"passed_time":0.470868444,"remaining_time":1.375674474},
{"learn":[4.604771557],"iteration":255,"passed_time":0.4718923736,"remaining_time":1.371437211},
{"learn":[4.604231277],"iteration":256,"passed_time":0.4729341505,"remaining_time":1.367276552},
{"learn":[4.600750354],"iteration":257,"passed_time":0.4740092813,"remaining_time":1.363235995},
{"learn":[4.596488253],"iteration":258,"passed_time":0.4751267806,"remaining_time":1.359339554},
{"learn":[4.59470784],"iteration":259,"passed_time":0.4762283146,"remaining_time":1.355419049},
{"learn":[4.588818005],"iteration":260,"passed_time":0.4774120711,"remaining_time":1.351752952},
{"learn":[4.585054174],"iteration":261,"passed_time":0.4784122765,"remaining_time":1.347588779},
{"learn":[4.581471435],"iteration":262,"passed_time":0.4794547422,"remaining_time":1.343567091},
{"learn":[4.577555199],"iteration":263,"passed_time":0.4805099535,"remaining_time":1.339603507},
{"learn":[4.57457145],"iteration":264,"passed_time":0.4821798591,"remaining_time":1.337366779},
{"learn":[4.573029224],"iteration":265,"passed_time":0.4835275311,"remaining_time":1.334245142},
{"learn":[4.571326203],"iteration":266,"passed_time":0.4846141907,"remaining_time":1.330420231},
{"learn":[4.571019224],"iteration":267,"passed_time":0.4855931639,"remaining_time":1.326321627},
{"learn":[4.565766631],"iteration":268,"passed_time":0.486604016,"remaining_time":1.322332846},
{"learn":[4.563383471],"iteration":269,"passed_time":0.4876105125,"remaining_time":1.318354349},
{"learn":[4.558165805],"iteration":270,"passed_time":0.4885349558,"remaining_time":1.314177058},
{"learn":[4.55629209],"iteration":271,"passed_time":0.4894819384,"remaining_time":1.310084012},
{"learn":[4.549383848],"iteration":272,"passed_time":0.4910255425,"remaining_time":1.307602818},
{"learn":[4.546227503],"iteration":273,"passed_time":0.4921384886,"remaining_time":1.303987382},
{"learn":[4.540620977],"iteration":274,"passed_time":0.494043946,"remaining_time":1.302479494},
{"learn":[4.532898237],"iteration":275,"passed_time":0.4954275013,"remaining_time":1.299599677},
{"learn":[4.529757367],"iteration":276,"passed_time":0.4969705884,"remaining_time":1.297147059},
{"learn":[4.52579294],"iteration":277,"passed_time":0.4982754755,"remaining_time":1.29408235},
{"learn":[4.521572155],"iteration":278,"passed_time":0.4993801826,"remaining_time":1.290512945},
{"learn":[4.518818099],"iteration":279,"passed_time":0.5004302572,"remaining_time":1.286820661},
{"learn":[4.514012334],"iteration":280,"passed_time":0.5014674658,"remaining_time":1.283114263},
{"learn":[4.508331416],"iteration":281,"passed_time":0.5024388105,"remaining_time":1.279259099},
{"learn":[4.506038537],"iteration":282,"passed_time":0.5034082147,"remaining_time":1.275419399},
{"learn":[4.505805643],"iteration":283,"passed_time":0.5048206652,"remaining_time":1.272716888},
{"learn":[4.501550352],"iteration":284,"passed_time":0.5059933046,"remaining_time":1.269421799},
{"learn":[4.494692643],"iteration":285,"passed_time":0.5073324073,"remaining_time":1.266557129},
{"learn":[4.489330245],"iteration":286,"passed_time":0.5084494762,"remaining_time":1.263151486},
{"learn":[4.484826955],"iteration":287,"passed_time":0.509565936,"remaining_time":1.259760231},
{"learn":[4.478285428],"iteration":288,"passed_time":0.5116708188,"remaining_time":1.258816444},
{"learn":[4.475311671],"iteration":289,"passed_time":0.5129225763,"remaining_time":1.255775963},
{"learn":[4.471581298],"iteration":290,"passed_time":0.5140505999,"remaining_time":1.252446307},
{"learn":[4.469164956],"iteration":291,"passed_time":0.5151406423,"remaining_time":1.24903964},
{"learn":[4.462068024],"iteration":292,"passed_time":0.516314552,"remaining_time":1.245851155},
{"learn":[4.458540976],"iteration":293,"passed_time":0.5174260678,"remaining_time":1.242526544},
{"learn":[4.455757458],"iteration":294,"passed_time":0.5184490007,"remaining_time":1.239005239},
{"learn":[4.453027414],"iteration":295,"passed_time":0.5196796225,"remaining_time":1.235994778},
{"learn":[4.450659338],"iteration":296,"passed_time":0.5207453019,"remaining_time":1.232605883},
{"learn":[4.444696901],"iteration":297,"passed_time":0.5217872477,"remaining_time":1.229176671},
{"learn":[4.442052813],"iteration":298,"passed_time":0.5228513905,"remaining_time":1.225815467},
{"learn":[4.440036756],"iteration":299,"passed_time":0.523862343,"remaining_time":1.222345467},
{"learn":[4.435017051],"iteration":300,"passed_time":0.524908123,"remaining_time":1.218972684},
{"learn":[4.429962125],"iteration":301,"passed_time":0.5261772265,"remaining_time":1.216131471},
{"learn":[4.427666256],"iteration":302,"passed_time":0.5273048425,"remaining_time":1.212975166},
{"learn":[4.425030004],"iteration":303,"passed_time":0.5283526761,"remaining_time":1.209649548},
{"learn":[4.422588771],"iteration":304,"passed_time":0.5292697008,"remaining_time":1.206040794},
{"learn":[4.418936667],"iteration":305,"passed_time":0.5302714266,"remaining_time":1.202641732},
{"learn":[4.416887976],"iteration":306,"passed_time":0.531272303,"remaining_time":1.199256371},
{"learn":[4.413773354],"iteration":307,"passed_time":0.5322879563,"remaining_time":1.195919694},
{"learn":[4.411129391],"iteration":308,"passed_time":0.533902334,"remaining_time":1.193936935},
{"learn":[4.40850819],"iteration":309,"passed_time":0.5349405466,"remaining_time":1.19067412},
{"learn":[4.404880292],"iteration":310,"passed_time":0.5359266468,"remaining_time":1.18731016},
{"learn":[4.404593827],"iteration":311,"passed_time":0.5369106807,"remaining_time":1.183956886},
{"learn":[4.402139942],"iteration":312,"passed_time":0.5378945123,"remaining_time":1.180618306},
{"learn":[4.400284725],"iteration":313,"passed_time":0.5389362296,"remaining_time":1.17742119},
{"learn":[4.395805521],"iteration":314,"passed_time":0.5399396602,"remaining_time":1.174154499},
{"learn":[4.392838833],"iteration":315,"passed_time":0.5414114369,"remaining_time":1.171915895},
{"learn":[4.389213061],"iteration":316,"passed_time":0.5426128045,"remaining_time":1.169099513},
{"learn":[4.3861981],"iteration":317,"passed_time":0.5437100201,"remaining_time":1.166069917},
{"learn":[4.385054234],"iteration":318,"passed_time":0.5447277196,"remaining_time":1.162882687},
{"learn":[4.379364607],"iteration":319,"passed_time":0.5456549403,"remaining_time":1.159516748},
{"learn":[4.378387619],"iteration":320,"passed_time":0.5465962231,"remaining_time":1.156195749},
{"learn":[4.375816727],"iteration":321,"passed_time":0.5477310033,"remaining_time":1.153296957},
{"learn":[4.374600202],"iteration":322,"passed_time":0.5487850904,"remaining_time":1.150239957},
{"learn":[4.37098897],"iteration":323,"passed_time":0.5497591723,"remaining_time":1.147028397},
{"learn":[4.367418484],"iteration":324,"passed_time":0.5508326393,"remaining_time":1.14403702},
{"learn":[4.363584638],"iteration":325,"passed_time":0.5518349936,"remaining_time":1.140910386},
{"learn":[4.360770706],"iteration":326,"passed_time":0.5528300334,"remaining_time":1.13778169},
{"learn":[4.358675808],"iteration":327,"passed_time":0.5537602732,"remaining_time":1.134533243},
{"learn":[4.354228195],"iteration":328,"passed_time":0.5547557459,"remaining_time":1.131431932},
{"learn":[4.353773425],"iteration":329,"passed_time":0.556100407,"remaining_time":1.129052341},
{"learn":[4.351648009],"iteration":330,"passed_time":0.5572496807,"remaining_time":1.126284098},
{"learn":[4.348209927],"iteration":331,"passed_time":0.558243326,"remaining_time":1.123212475},
{"learn":[4.345852733],"iteration":332,"passed_time":0.5592614606,"remaining_time":1.120202385},
{"learn":[4.34237339],"iteration":333,"passed_time":0.5602840885,"remaining_time":1.117213182},
{"learn":[4.340814362],"iteration":334,"passed_time":0.5613869949,"remaining_time":1.114395079},
{"learn":[4.339707068],"iteration":335,"passed_time":0.5628893954,"remaining_time":1.112376662},
{"learn":[4.335430786],"iteration":336,"passed_time":0.5641856206,"remaining_time":1.109955687},
{"learn":[4.33521887],"iteration":337,"passed_time":0.5654138942,"remaining_time":1.107408278},
{"learn":[4.328507238],"iteration":338,"passed_time":0.5666614775,"remaining_time":1.104906303},
{"learn":[4.326140732],"iteration":339,"passed_time":0.5676959861,"remaining_time":1.101998091},
{"learn":[4.323785636],"iteration":340,"passed_time":0.5687018972,"remaining_time":1.099045602},
{"learn":[4.320632534],"iteration":341,"passed_time":0.569773495,"remaining_time":1.096230876},
{"learn":[4.31973724],"iteration":342,"passed_time":0.5712033897,"remaining_time":1.094112615},
{"learn":[4.318000924],"iteration":343,"passed_time":0.5725129601,"remaining_time":1.091768901},
{"learn":[4.312713628],"iteration":344,"passed_time":0.5735163103,"remaining_time":1.088849807},
{"learn":[4.308220789],"iteration":345,"passed_time":0.5745716235,"remaining_time":1.086040005},
{"learn":[4.305890947],"iteration":346,"passed_time":0.5757367074,"remaining_time":1.083446887},
{"learn":[4.305137856],"iteration":347,"passed_time":0.5767123535,"remaining_time":1.080507053},
{"learn":[4.304787172],"iteration":348,"passed_time":0.577681934,"remaining_time":1.077567161},
{"learn":[4.30350134],"iteration":349,"passed_time":0.5786280307,"remaining_time":1.074594914},
{"learn":[4.30293809],"iteration":350,"passed_time":0.5795656347,"remaining_time":1.07161851},
{"learn":[4.299548459],"iteration":351,"passed_time":0.5805962919,"remaining_time":1.068824992},
{"learn":[4.294768408],"iteration":352,"passed_time":0.5817270474,"remaining_time":1.066224928},
{"learn":[4.294581479],"iteration":353,"passed_time":0.5826707082,"remaining_time":1.063291744},
{"learn":[4.292551604],"iteration":354,"passed_time":0.5836671099,"remaining_time":1.060465594},
{"learn":[4.288628894],"iteration":355,"passed_time":0.584663281,"remaining_time":1.057649306},
{"learn":[4.287802767],"iteration":356,"passed_time":0.5857232459,"remaining_time":1.054958115},
{"learn":[4.284566905],"iteration":357,"passed_time":0.5869399796,"remaining_time":1.05255717},
{"learn":[4.27890232],"iteration":358,"passed_time":0.5879836889,"remaining_time":1.049853885},
{"learn":[4.276938023],"iteration":359,"passed_time":0.5891224186,"remaining_time":1.047328744},
{"learn":[4.273425094],"iteration":360,"passed_time":0.5901378414,"remaining_time":1.044593021},
{"learn":[4.269726505],"iteration":361,"passed_time":0.5910504799,"remaining_time":1.041685652},
{"learn":[4.265565857],"iteration":362,"passed_time":0.5920650131,"remaining_time":1.038968081},
{"learn":[4.262117173],"iteration":363,"passed_time":0.5930423425,"remaining_time":1.036194862},
{"learn":[4.259185148],"iteration":364,"passed_time":0.5940457567,"remaining_time":1.033476864},
{"learn":[4.257668507],"iteration":365,"passed_time":0.5951606129,"remaining_time":1.03096128},
{"learn":[4.253432436],"iteration":366,"passed_time":0.5964741343,"remaining_time":1.028795986},
{"learn":[4.250216667],"iteration":367,"passed_time":0.597531025,"remaining_time":1.026194586},
{"learn":[4.24514828],"iteration":368,"passed_time":0.5985478908,"remaining_time":1.023533114},
{"learn":[4.244015772],"iteration":369,"passed_time":0.5994907527,"remaining_time":1.020754525},
{"learn":[4.240329192],"iteration":370,"passed_time":0.6005350823,"remaining_time":1.018157862},
{"learn":[4.236718014],"iteration":371,"passed_time":0.6019709854,"remaining_time":1.016230588},
{"learn":[4.233495944],"iteration":372,"passed_time":0.6030322943,"remaining_time":1.013676269},
{"learn":[4.230357491],"iteration":373,"passed_time":0.6043864019,"remaining_time":1.01162002},
{"learn":[4.227381215],"iteration":374,"passed_time":0.6056328751,"remaining_time":1.009388125},
{"learn":[4.226169067],"iteration":375,"passed_time":0.6067908509,"remaining_time":1.007014604},
{"learn":[4.225963861],"iteration":376,"passed_time":0.6082416767,"remaining_time":1.005131471},
{"learn":[4.224346548],"iteration":377,"passed_time":0.6099609706,"remaining_time":1.003692391},
{"learn":[4.222595381],"iteration":378,"passed_time":0.6111164863,"remaining_time":1.001328069},
{"learn":[4.219700938],"iteration":379,"passed_time":0.6121501105,"remaining_time":0.9987712329},
{"learn":[4.216356207],"iteration":380,"passed_time":0.6132087923,"remaining_time":0.9962631035},
{"learn":[4.214326494],"iteration":381,"passed_time":0.6144842195,"remaining_time":0.9941132138},
{"learn":[4.212901398],"iteration":382,"passed_time":0.6164870025,"remaining_time":0.9931396358},
{"learn":[4.211331091],"iteration":383,"passed_time":0.6179382987,"remaining_time":0.9912760209},
{"learn":[4.208624791],"iteration":384,"passed_time":0.6189418,"remaining_time":0.9886992389},
{"learn":[4.204659106],"iteration":385,"passed_time":0.6199431003,"remaining_time":0.9861271078},
{"learn":[4.202968852],"iteration":386,"passed_time":0.6209676085,"remaining_time":0.9835998554},
{"learn":[4.197261935],"iteration":387,"passed_time":0.622177988,"remaining_time":0.9813735274},
{"learn":[4.196934403],"iteration":388,"passed_time":0.6230777887,"remaining_time":0.9786645987},
{"learn":[4.192479929],"iteration":389,"passed_time":0.6240815547,"remaining_time":0.9761275599},
{"learn":[4.190243116],"iteration":390,"passed_time":0.6251033488,"remaining_time":0.9736264435},
{"learn":[4.185852431],"iteration":391,"passed_time":0.6262678544,"remaining_time":0.9713542231},
{"learn":[4.180967944],"iteration":392,"passed_time":0.628490424,"remaining_time":0.9707218509},
{"learn":[4.178283162],"iteration":393,"passed_time":0.6295551046,"remaining_time":0.9683004908},
{"learn":[4.176341157],"iteration":394,"passed_time":0.6310478127,"remaining_time":0.9665415866},
{"learn":[4.176041504],"iteration":395,"passed_time":0.6324269888,"remaining_time":0.9646108618},
{"learn":[4.175564513],"iteration":396,"passed_time":0.6336209624,"remaining_time":0.9624016129},
{"learn":[4.170830274],"iteration":397,"passed_time":0.634710116,"remaining_time":0.9600389192},
{"learn":[4.167804808],"iteration":398,"passed_time":0.635655872,"remaining_time":0.9574666143},
{"learn":[4.165860548],"iteration":399,"passed_time":0.6366145158,"remaining_time":0.9549217737},
{"learn":[4.160950571],"iteration":400,"passed_time":0.6375592387,"remaining_time":0.9523640498},
{"learn":[4.158544115],"iteration":401,"passed_time":0.6385710875,"remaining_time":0.9499142048},
{"learn":[4.154448767],"iteration":402,"passed_time":0.6395849974,"remaining_time":0.9474745495},
{"learn":[4.15197457],"iteration":403,"passed_time":0.6406167591,"remaining_time":0.9450682882},
{"learn":[4.149562679],"iteration":404,"passed_time":0.6416704449,"remaining_time":0.942701024},
{"learn":[4.149327961],"iteration":405,"passed_time":0.6426317098,"remaining_time":0.9402050138},
{"learn":[4.147444889],"iteration":406,"passed_time":0.6435533297,"remaining_time":0.9376587825},
{"learn":[4.147254809],"iteration":407,"passed_time":0.6444432067,"remaining_time":0.9350744567},
{"learn":[4.144589165],"iteration":408,"passed_time":0.6457889938,"remaining_time":0.9331572014},
{"learn":[4.141691034],"iteration":409,"passed_time":0.6477669627,"remaining_time":0.9321524585},
{"learn":[4.138893468],"iteration":410,"passed_time":0.6489163804,"remaining_time":0.9299555913},
{"learn":[4.136964597],"iteration":411,"passed_time":0.6498939923,"remaining_time":0.9275186104},
{"learn":[4.133773523],"iteration":412,"passed_time":0.650846415,"remaining_time":0.9250528949},
{"learn":[4.131363444],"iteration":413,"passed_time":0.6518766088,"remaining_time":0.9227045718},
{"learn":[4.130228592],"iteration":414,"passed_time":0.652982314,"remaining_time":0.9204690451},
{"learn":[4.12884186],"iteration":415,"passed_time":0.6539755613,"remaining_time":0.9180810765},
{"learn":[4.12413494],"iteration":416,"passed_time":0.654944886,"remaining_time":0.9156663514},
{"learn":[4.119422508],"iteration":417,"passed_time":0.6559806389,"remaining_time":0.9133510331},
{"learn":[4.117038244],"iteration":418,"passed_time":0.656983098,"remaining_time":0.9109956562},
{"learn":[4.116067631],"iteration":419,"passed_time":0.6580457123,"remaining_time":0.9087297932},
{"learn":[4.110343455],"iteration":420,"passed_time":0.6590189984,"remaining_time":0.9063467935},
{"learn":[4.105604544],"iteration":421,"passed_time":0.6601267945,"remaining_time":0.904154709},
{"learn":[4.103390131],"iteration":422,"passed_time":0.6622735038,"remaining_time":0.9033848977},
{"learn":[4.096724402],"iteration":423,"passed_time":0.6633301715,"remaining_time":0.9011277801},
{"learn":[4.093431279],"iteration":424,"passed_time":0.6646285213,"remaining_time":0.8992032936},
{"learn":[4.091412744],"iteration":425,"passed_time":0.6658948166,"remaining_time":0.8972385557},
{"learn":[4.091192901],"iteration":426,"passed_time":0.6670320963,"remaining_time":0.8951039607},
{"learn":[4.088994581],"iteration":427,"passed_time":0.6680742533,"remaining_time":0.8928468993},
{"learn":[4.087845355],"iteration":428,"passed_time":0.669111145,"remaining_time":0.8905884936},
{"learn":[4.083650279],"iteration":429,"passed_time":0.6708230865,"remaining_time":0.889230603},
{"learn":[4.079840652],"iteration":430,"passed_time":0.6726771537,"remaining_time":0.8880587017},
{"learn":[4.075707828],"iteration":431,"passed_time":0.6738654766,"remaining_time":0.8860083119},
{"learn":[4.071345409],"iteration":432,"passed_time":0.6749583187,"remaining_time":0.8838368746},
{"learn":[4.067460475],"iteration":433,"passed_time":0.6769258175,"remaining_time":0.8828110892},
{"learn":[4.064914749],"iteration":434,"passed_time":0.6784955017,"remaining_time":0.8812642723},
{"learn":[4.063823175],"iteration":435,"passed_time":0.6796048292,"remaining_time":0.8791218433},
{"learn":[4.058898471],"iteration":436,"passed_time":0.6807236877,"remaining_time":0.8769964215},
{"learn":[4.054120355],"iteration":437,"passed_time":0.6817733496,"remaining_time":0.8747868093},
{"learn":[4.052715901],"iteration":438,"passed_time":0.6828019576,"remaining_time":0.8725555768},
{"learn":[4.052114167],"iteration":439,"passed_time":0.6837598219,"remaining_time":0.8702397733},
{"learn":[4.051377267],"iteration":440,"passed_time":0.6847113445,"remaining_time":0.8679220898},
{"learn":[4.049275336],"iteration":441,"passed_time":0.6857405171,"remaining_time":0.8657086166},
{"learn":[4.047099198],"iteration":442,"passed_time":0.6867526002,"remaining_time":0.863479003},
{"learn":[4.044348685],"iteration":443,"passed_time":0.6877586705,"remaining_time":0.8612473442},
{"learn":[4.042822379],"iteration":444,"passed_time":0.6899035925,"remaining_time":0.8604415592},
{"learn":[4.041258611],"iteration":445,"passed_time":0.6909653797,"remaining_time":0.8582843506},
{"learn":[4.040044254],"iteration":446,"passed_time":0.6924208662,"remaining_time":0.8566191029},
{"learn":[4.036860137],"iteration":447,"passed_time":0.693454291,"remaining_time":0.8544347514},
{"learn":[4.036372284],"iteration":448,"passed_time":0.6945680608,"remaining_time":0.8523541236},
{"learn":[4.03368231],"iteration":449,"passed_time":0.6963317087,"remaining_time":0.8510720884},
{"learn":[4.032439519],"iteration":450,"passed_time":0.6973989925,"remaining_time":0.848940237},
{"learn":[4.032008634],"iteration":451,"passed_time":0.6983984892,"remaining_time":0.8467309116},
{"learn":[4.030034932],"iteration":452,"passed_time":0.6994159261,"remaining_time":0.8445485907},
{"learn":[4.028173412],"iteration":453,"passed_time":0.7007787231,"remaining_time":0.8427867463},
{"learn":[4.023806097],"iteration":454,"passed_time":0.7025235489,"remaining_time":0.8414842509},
{"learn":[4.020239186],"iteration":455,"passed_time":0.703584602,"remaining_time":0.8393640866},
{"learn":[4.017384838],"iteration":456,"passed_time":0.7045752735,"remaining_time":0.8371649311},
{"learn":[4.016468229],"iteration":457,"passed_time":0.7061267935,"remaining_time":0.8356347643},
{"learn":[4.014530169],"iteration":458,"passed_time":0.7083797739,"remaining_time":0.8349312804},
{"learn":[4.012884822],"iteration":459,"passed_time":0.7095243075,"remaining_time":0.8329198392},
{"learn":[4.008924707],"iteration":460,"passed_time":0.7106622324,"remaining_time":0.8309044323},
{"learn":[4.008286778],"iteration":461,"passed_time":0.7116765573,"remaining_time":0.8287488915},
{"learn":[4.006444202],"iteration":462,"passed_time":0.7126876051,"remaining_time":0.8265944794},
{"learn":[4.003284363],"iteration":463,"passed_time":0.713692556,"remaining_time":0.8244379526},
{"learn":[3.999811484],"iteration":464,"passed_time":0.7149876149,"remaining_time":0.8226201591},
{"learn":[3.997483319],"iteration":465,"passed_time":0.7162841198,"remaining_time":0.820806266},
{"learn":[3.99708333],"iteration":466,"passed_time":0.7172970382,"remaining_time":0.8186709237},
{"learn":[3.995860263],"iteration":467,"passed_time":0.7182726606,"remaining_time":0.8164979817},
{"learn":[3.994131111],"iteration":468,"passed_time":0.7194038824,"remaining_time":0.8145063147},
{"learn":[3.993125499],"iteration":469,"passed_time":0.7208340806,"remaining_time":0.8128554526},
{"learn":[3.992954084],"iteration":470,"passed_time":0.7219603563,"remaining_time":0.8108641793},
{"learn":[3.990635743],"iteration":471,"passed_time":0.7233956319,"remaining_time":0.8092222323},
{"learn":[3.986678254],"iteration":472,"passed_time":0.7246087329,"remaining_time":0.80733362},
{"learn":[3.986393291],"iteration":473,"passed_time":0.7258874533,"remaining_time":0.805520676},
{"learn":[3.986152671],"iteration":474,"passed_time":0.7270064026,"remaining_time":0.8035333923},
{"learn":[3.985596662],"iteration":475,"passed_time":0.7280451708,"remaining_time":0.8014614905},
{"learn":[3.983853457],"iteration":476,"passed_time":0.729037016,"remaining_time":0.7993424725},
{"learn":[3.983263928],"iteration":477,"passed_time":0.7304078914,"remaining_time":0.7976420906},
{"learn":[3.980067202],"iteration":478,"passed_time":0.7317102775,"remaining_time":0.7958685899},
{"learn":[3.978115407],"iteration":479,"passed_time":0.7328692964,"remaining_time":0.7939417378},
{"learn":[3.972661644],"iteration":480,"passed_time":0.7341102785,"remaining_time":0.7921065167},
{"learn":[3.969938254],"iteration":481,"passed_time":0.7353595904,"remaining_time":0.7902827133},
{"learn":[3.968211434],"iteration":482,"passed_time":0.7366014784,"remaining_time":0.7884533423},
{"learn":[3.966113368],"iteration":483,"passed_time":0.739249758,"remaining_time":0.7881257751},
{"learn":[3.962246044],"iteration":484,"passed_time":0.7416218467,"remaining_time":0.787495363},
{"learn":[3.961319703],"iteration":485,"passed_time":0.7428338718,"remaining_time":0.785630885},
{"learn":[3.96078191],"iteration":486,"passed_time":0.7439268891,"remaining_time":0.783643725},
{"learn":[3.958913633],"iteration":487,"passed_time":0.7457130348,"remaining_time":0.7823874464},
{"learn":[3.957428286],"iteration":488,"passed_time":0.7473463967,"remaining_time":0.780969343},
{"learn":[3.952641965],"iteration":489,"passed_time":0.748639569,"remaining_time":0.7791962861},
{"learn":[3.951486786],"iteration":490,"passed_time":0.7514328785,"remaining_time":0.778980316},
{"learn":[3.94938344],"iteration":491,"passed_time":0.7536105579,"remaining_time":0.7781182183},
{"learn":[3.947297924],"iteration":492,"passed_time":0.7552180677,"remaining_time":0.7766644226},
{"learn":[3.946284886],"iteration":493,"passed_time":0.7564567047,"remaining_time":0.7748321712},
{"learn":[3.943288204],"iteration":494,"passed_time":0.7575198314,"remaining_time":0.7728232624},
{"learn":[3.943076488],"iteration":495,"passed_time":0.7587208643,"remaining_time":0.7709582976},
{"learn":[3.942347078],"iteration":496,"passed_time":0.7597974359,"remaining_time":0.7689700408},
{"learn":[3.940251541],"iteration":497,"passed_time":0.7610193561,"remaining_time":0.7671319613},
{"learn":[3.939011019],"iteration":498,"passed_time":0.762249458,"remaining_time":0.765304566},
{"learn":[3.938760512],"iteration":499,"passed_time":0.7640604308,"remaining_time":0.7640604308},
{"learn":[3.934522727],"iteration":500,"passed_time":0.766028817,"remaining_time":0.7629708177},
{"learn":[3.930091193],"iteration":501,"passed_time":0.7674765631,"remaining_time":0.761361212},
{"learn":[3.927671752],"iteration":502,"passed_time":0.7686220465,"remaining_time":0.7594535927},
{"learn":[3.927280041],"iteration":503,"passed_time":0.7697160236,"remaining_time":0.757498309},
{"learn":[3.925987561],"iteration":504,"passed_time":0.7715192912,"remaining_time":0.7562416815},
{"learn":[3.921645957],"iteration":505,"passed_time":0.7732203257,"remaining_time":0.7548830848},
{"learn":[3.920333743],"iteration":506,"passed_time":0.7743620224,"remaining_time":0.7529792447},
{"learn":[3.918659461],"iteration":507,"passed_time":0.7757295901,"remaining_time":0.7512971621},
{"learn":[3.916124385],"iteration":508,"passed_time":0.7771308733,"remaining_time":0.7496488385},
{"learn":[3.913849268],"iteration":509,"passed_time":0.778282763,"remaining_time":0.7477618703},
{"learn":[3.912826119],"iteration":510,"passed_time":0.7793585908,"remaining_time":0.745804992},
{"learn":[3.910034145],"iteration":511,"passed_time":0.7820778879,"remaining_time":0.7454179869},
{"learn":[3.90792379],"iteration":512,"passed_time":0.7835775245,"remaining_time":0.7438640437},
{"learn":[3.907823851],"iteration":513,"passed_time":0.7848776817,"remaining_time":0.7421216991},
{"learn":[3.904527401],"iteration":514,"passed_time":0.7863408649,"remaining_time":0.740534601},
{"learn":[3.903378283],"iteration":515,"passed_time":0.7873655784,"remaining_time":0.7385367054},
{"learn":[3.902170135],"iteration":516,"passed_time":0.7884478936,"remaining_time":0.736596388},
{"learn":[3.899435429],"iteration":517,"passed_time":0.7896099681,"remaining_time":0.7347335996},
{"learn":[3.897497505],"iteration":518,"passed_time":0.7906641857,"remaining_time":0.7327735517},
{"learn":[3.896426119],"iteration":519,"passed_time":0.7917099381,"remaining_time":0.7308091737},
{"learn":[3.896044669],"iteration":520,"passed_time":0.7926835024,"remaining_time":0.7287819533},
{"learn":[3.892795942],"iteration":521,"passed_time":0.7937203769,"remaining_time":0.7268167436},
{"learn":[3.892413888],"iteration":522,"passed_time":0.7951233842,"remaining_time":0.7251890139},
{"learn":[3.891738985],"iteration":523,"passed_time":0.7962193659,"remaining_time":0.7232832408},
{"learn":[3.88822057],"iteration":524,"passed_time":0.797354814,"remaining_time":0.7214162603},
{"learn":[3.883837053],"iteration":525,"passed_time":0.7986690078,"remaining_time":0.7197131363},
{"learn":[3.881769742],"iteration":526,"passed_time":0.799759183,"remaining_time":0.7178104242},
{"learn":[3.880356898],"iteration":527,"passed_time":0.8008899656,"remaining_time":0.7159470905},
{"learn":[3.879250273],"iteration":528,"passed_time":0.8021127211,"remaining_time":0.7141684152},
{"learn":[3.877174493],"iteration":529,"passed_time":0.8031861687,"remaining_time":0.7122594326},
{"learn":[3.875854201],"iteration":530,"passed_time":0.8042380389,"remaining_time":0.7103345391},
{"learn":[3.873189396],"iteration":531,"passed_time":0.8053521967,"remaining_time":0.7084677219},
{"learn":[3.871583368],"iteration":532,"passed_time":0.8065149383,"remaining_time":0.7066462968},
{"learn":[3.869622679],"iteration":533,"passed_time":0.8075485602,"remaining_time":0.7047146612},
{"learn":[3.866860164],"iteration":534,"passed_time":0.8085397517,"remaining_time":0.7027495038},
{"learn":[3.864498444],"iteration":535,"passed_time":0.8096542062,"remaining_time":0.700894686},
{"learn":[3.861416322],"iteration":536,"passed_time":0.8108744141,"remaining_time":0.6991338058},
{"learn":[3.860265769],"iteration":537,"passed_time":0.8119863799,"remaining_time":0.6972819842},
{"learn":[3.859328725],"iteration":538,"passed_time":0.8131357496,"remaining_time":0.695464899},
{"learn":[3.858521278],"iteration":539,"passed_time":0.8141649244,"remaining_time":0.6935478986},
{"learn":[3.85599111],"iteration":540,"passed_time":0.8151717549,"remaining_time":0.6916152227},
{"learn":[3.852379816],"iteration":541,"passed_time":0.816455404,"remaining_time":0.6899198801},
{"learn":[3.851327537],"iteration":542,"passed_time":0.8176409496,"remaining_time":0.688143488},
{"learn":[3.847854898],"iteration":543,"passed_time":0.8186290231,"remaining_time":0.6862037399},
{"learn":[3.847083414],"iteration":544,"passed_time":0.8196329825,"remaining_time":0.6842807468},
{"learn":[3.845397429],"iteration":545,"passed_time":0.820824246,"remaining_time":0.6825168639},
{"learn":[3.841933528],"iteration":546,"passed_time":0.8219067635,"remaining_time":0.6806650162},
{"learn":[3.840996474],"iteration":547,"passed_time":0.8229294881,"remaining_time":0.6787666581},
{"learn":[3.838355966],"iteration":548,"passed_time":0.8239619274,"remaining_time":0.6768794704},
{"learn":[3.83342799],"iteration":549,"passed_time":0.8255340877,"remaining_time":0.6754369808},
{"learn":[3.828161535],"iteration":550,"passed_time":0.826738834,"remaining_time":0.6736946215},
{"learn":[3.823502399],"iteration":551,"passed_time":0.828140765,"remaining_time":0.672114244},
{"learn":[3.820068862],"iteration":552,"passed_time":0.8294020728,"remaining_time":0.6704208436},
{"learn":[3.817951642],"iteration":553,"passed_time":0.8305351601,"remaining_time":0.6686257787},
{"learn":[3.815785958],"iteration":554,"passed_time":0.8319236946,"remaining_time":0.6670379173},
{"learn":[3.81503012],"iteration":555,"passed_time":0.832937339,"remaining_time":0.6651514002},
{"learn":[3.813529315],"iteration":556,"passed_time":0.8339464819,"remaining_time":0.6632644371},
{"learn":[3.808881326],"iteration":557,"passed_time":0.8349553377,"remaining_time":0.6613803929},
{"learn":[3.808740434],"iteration":558,"passed_time":0.8359070039,"remaining_time":0.6594543627},
{"learn":[3.80714352],"iteration":559,"passed_time":0.8374699731,"remaining_time":0.6580121217},
{"learn":[3.80573346],"iteration":560,"passed_time":0.8384690562,"remaining_time":0.6561281919},
{"learn":[3.803370052],"iteration":561,"passed_time":0.8394706912,"remaining_time":0.6542493999},
{"learn":[3.803215211],"iteration":562,"passed_time":0.8408917028,"remaining_time":0.6526992436},
{"learn":[3.801309667],"iteration":563,"passed_time":0.8420361702,"remaining_time":0.6509357628},
{"learn":[3.800003847],"iteration":564,"passed_time":0.8431569685,"remaining_time":0.6491562501},
{"learn":[3.798026138],"iteration":565,"passed_time":0.8441888381,"remaining_time":0.6473108758},
{"learn":[3.794745847],"iteration":566,"passed_time":0.845458325,"remaining_time":0.6456498319},
{"learn":[3.794312041],"iteration":567,"passed_time":0.8464567587,"remaining_time":0.6437840137},
{"learn":[3.792205926],"iteration":568,"passed_time":0.8474662021,"remaining_time":0.6419295837},
{"learn":[3.788991061],"iteration":569,"passed_time":0.8486339822,"remaining_time":0.6401975656},
{"learn":[3.787391572],"iteration":570,"passed_time":0.8498869632,"remaining_time":0.6385315363},
{"learn":[3.7826445],"iteration":571,"passed_time":0.8509978308,"remaining_time":0.6367606147},
{"learn":[3.781700331],"iteration":572,"passed_time":0.8520668105,"remaining_time":0.634960782},
{"learn":[3.780045374],"iteration":573,"passed_time":0.8530846298,"remaining_time":0.6331255266},
{"learn":[3.775462644],"iteration":574,"passed_time":0.8541226981,"remaining_time":0.6313080812},
{"learn":[3.773711943],"iteration":575,"passed_time":0.8559445531,"remaining_time":0.630070296},
{"learn":[3.772415806],"iteration":576,"passed_time":0.8573880246,"remaining_time":0.6285530926},
{"learn":[3.770170875],"iteration":577,"passed_time":0.8585251552,"remaining_time":0.6268124836},
{"learn":[3.765166479],"iteration":578,"passed_time":0.8601251516,"remaining_time":0.6254105161},
{"learn":[3.763976102],"iteration":579,"passed_time":0.8612424608,"remaining_time":0.6236583337},
{"learn":[3.760761708],"iteration":580,"passed_time":0.8624125541,"remaining_time":0.621946403},
{"learn":[3.758155662],"iteration":581,"passed_time":0.8634985719,"remaining_time":0.6201759502},
{"learn":[3.756844548],"iteration":582,"passed_time":0.8645440097,"remaining_time":0.61837882},
{"learn":[3.753098923],"iteration":583,"passed_time":0.8656409739,"remaining_time":0.6166209677},
{"learn":[3.751618946],"iteration":584,"passed_time":0.8666810326,"remaining_time":0.614825006},
{"learn":[3.751398464],"iteration":585,"passed_time":0.8677617397,"remaining_time":0.6130603417},
{"learn":[3.749920103],"iteration":586,"passed_time":0.8693027777,"remaining_time":0.6116218862},
{"learn":[3.748237465],"iteration":587,"passed_time":0.8709646745,"remaining_time":0.6102677651},
{"learn":[3.746021536],"iteration":588,"passed_time":0.8722237245,"remaining_time":0.6086314954},
{"learn":[3.74417648],"iteration":589,"passed_time":0.8736556933,"remaining_time":0.6071166682},
{"learn":[3.738788389],"iteration":590,"passed_time":0.87499892,"remaining_time":0.6055407077},
{"learn":[3.736021611],"iteration":591,"passed_time":0.8760233508,"remaining_time":0.6037458229},
{"learn":[3.734546151],"iteration":592,"passed_time":0.8770642709,"remaining_time":0.6019648537},
{"learn":[3.733527479],"iteration":593,"passed_time":0.8782441313,"remaining_time":0.6002813423},
{"learn":[3.733026392],"iteration":594,"passed_time":0.8792319816,"remaining_time":0.5984688278},
{"learn":[3.730314752],"iteration":595,"passed_time":0.8803032321,"remaining_time":0.5967156137},
{"learn":[3.727342596],"iteration":596,"passed_time":0.8813625789,"remaining_time":0.5949566487},
{"learn":[3.725459604],"iteration":597,"passed_time":0.8824039237,"remaining_time":0.5931879219},
{"learn":[3.723158842],"iteration":598,"passed_time":0.8834349594,"remaining_time":0.5914147224},
{"learn":[3.722362756],"iteration":599,"passed_time":0.8846020389,"remaining_time":0.5897346926},
{"learn":[3.721443615],"iteration":600,"passed_time":0.8862151416,"remaining_time":0.5883524817},
{"learn":[3.720743486],"iteration":601,"passed_time":0.8874852619,"remaining_time":0.5867427479},
{"learn":[3.720215334],"iteration":602,"passed_time":0.8890643019,"remaining_time":0.5853375254},
{"learn":[3.719436563],"iteration":603,"passed_time":0.8903082725,"remaining_time":0.5837120462},
{"learn":[3.715046574],"iteration":604,"passed_time":0.8914523546,"remaining_time":0.5820226117},
{"learn":[3.71443396],"iteration":605,"passed_time":0.892587272,"remaining_time":0.5803290185},
{"learn":[3.712938941],"iteration":606,"passed_time":0.8936846695,"remaining_time":0.5786129738},
{"learn":[3.712814764],"iteration":607,"passed_time":0.8947115274,"remaining_time":0.5768534847},
{"learn":[3.71235348],"iteration":608,"passed_time":0.8957795007,"remaining_time":0.5751227993},
{"learn":[3.711223749],"iteration":609,"passed_time":0.8968775449,"remaining_time":0.5734135123},
{"learn":[3.710755648],"iteration":610,"passed_time":0.8979455543,"remaining_time":0.5716871041},
{"learn":[3.708668039],"iteration":611,"passed_time":0.8989967193,"remaining_time":0.5699521685},
{"learn":[3.705623591],"iteration":612,"passed_time":0.9003475851,"remaining_time":0.5684086712},
{"learn":[3.704045802],"iteration":613,"passed_time":0.901688721,"remaining_time":0.5668596845},
{"learn":[3.699915209],"iteration":614,"passed_time":0.903247371,"remaining_time":0.5654475412},
{"learn":[3.696182221],"iteration":615,"passed_time":0.9044760433,"remaining_time":0.5638292218},
{"learn":[3.694263278],"iteration":616,"passed_time":0.9056321871,"remaining_time":0.5621671437},
{"learn":[3.693810229],"iteration":617,"passed_time":0.9067299122,"remaining_time":0.560470593},
{"learn":[3.690900932],"iteration":618,"passed_time":0.9077652873,"remaining_time":0.5587376001},
{"learn":[3.688020895],"iteration":619,"passed_time":0.9088187678,"remaining_time":0.5570179544},
{"learn":[3.685491894],"iteration":620,"passed_time":0.9098413971,"remaining_time":0.5552816256},
{"learn":[3.684328128],"iteration":621,"passed_time":0.9108319125,"remaining_time":0.5535280754},
{"learn":[3.680640153],"iteration":622,"passed_time":0.9118781053,"remaining_time":0.5518106672},
{"learn":[3.678932783],"iteration":623,"passed_time":0.9128669895,"remaining_time":0.5500608783},
{"learn":[3.674167041],"iteration":624,"passed_time":0.9138706395,"remaining_time":0.5483223837},
{"learn":[3.672200976],"iteration":625,"passed_time":0.9155029027,"remaining_time":0.5469617981},
{"learn":[3.670606604],"iteration":626,"passed_time":0.9166556418,"remaining_time":0.5453150788},
{"learn":[3.665506042],"iteration":627,"passed_time":0.9177608309,"remaining_time":0.5436417661},
{"learn":[3.664214007],"iteration":628,"passed_time":0.918882254,"remaining_time":0.5419798351},
{"learn":[3.66261643],"iteration":629,"passed_time":0.9199309214,"remaining_time":0.5402768904},
{"learn":[3.662118449],"iteration":630,"passed_time":0.9209200979,"remaining_time":0.53854123},
{"learn":[3.660871366],"iteration":631,"passed_time":0.9219086259,"remaining_time":0.5368075543},
{"learn":[3.656695243],"iteration":632,"passed_time":0.9228832828,"remaining_time":0.5350681908},
{"learn":[3.654497801],"iteration":633,"passed_time":0.9238899109,"remaining_time":0.5333496962},
{"learn":[3.654189134],"iteration":634,"passed_time":0.9249060061,"remaining_time":0.5316388854},
{"learn":[3.653957699],"iteration":635,"passed_time":0.9258285631,"remaining_time":0.5298767248},
{"learn":[3.651920725],"iteration":636,"passed_time":0.9268303559,"remaining_time":0.5281623535},
{"learn":[3.65106705],"iteration":637,"passed_time":0.9278596125,"remaining_time":0.5264657989},
{"learn":[3.650612844],"iteration":638,"passed_time":0.9287415361,"remaining_time":0.5246880978},
{"learn":[3.649884732],"iteration":639,"passed_time":0.9298665837,"remaining_time":0.5230499533},
{"learn":[3.646276182],"iteration":640,"passed_time":0.9312360488,"remaining_time":0.5215502988},
{"learn":[3.645808194],"iteration":641,"passed_time":0.9322795365,"remaining_time":0.5198692742},
{"learn":[3.645042989],"iteration":642,"passed_time":0.9334168188,"remaining_time":0.5182423084},
{"learn":[3.639864499],"iteration":643,"passed_time":0.9345502772,"remaining_time":0.5166147495},
{"learn":[3.637318478],"iteration":644,"passed_time":0.9356951637,"remaining_time":0.5149950126},
{"learn":[3.636344905],"iteration":645,"passed_time":0.9367453291,"remaining_time":0.5133248398},
{"learn":[3.634754643],"iteration":646,"passed_time":0.9377893515,"remaining_time":0.511653232},
{"learn":[3.630724975],"iteration":647,"passed_time":0.9388384131,"remaining_time":0.5099862985},
{"learn":[3.629408252],"iteration":648,"passed_time":0.9402858662,"remaining_time":0.508536732},
{"learn":[3.62790646],"iteration":649,"passed_time":0.9413514497,"remaining_time":0.5068815499},
{"learn":[3.627388973],"iteration":650,"passed_time":0.9424184703,"remaining_time":0.5052289495},
{"learn":[3.625163557],"iteration":651,"passed_time":0.9434606168,"remaining_time":0.5035648691},
{"learn":[3.623701985],"iteration":652,"passed_time":0.9444016096,"remaining_time":0.5018489411},
{"learn":[3.622342639],"iteration":653,"passed_time":0.9458710924,"remaining_time":0.5004149816},
{"learn":[3.621130639],"iteration":654,"passed_time":0.9470441962,"remaining_time":0.4988248056},
{"learn":[3.619125665],"iteration":655,"passed_time":0.9482021865,"remaining_time":0.4972279758},
{"learn":[3.618878783],"iteration":656,"passed_time":0.9492966597,"remaining_time":0.4955993216},
{"learn":[3.616207429],"iteration":657,"passed_time":0.9505042856,"remaining_time":0.4940311029},
{"learn":[3.61206486],"iteration":658,"passed_time":0.9515254929,"remaining_time":0.492367516},
{"learn":[3.611955873],"iteration":659,"passed_time":0.9526755521,"remaining_time":0.4907722541},
{"learn":[3.610713743],"iteration":660,"passed_time":0.9537862062,"remaining_time":0.48915813},
{"learn":[3.610044025],"iteration":661,"passed_time":0.9548099669,"remaining_time":0.4875011613},
{"learn":[3.607342669],"iteration":662,"passed_time":0.9558960196,"remaining_time":0.4858777656},
{"learn":[3.602510618],"iteration":663,"passed_time":0.9569244328,"remaining_time":0.4842268214},
{"learn":[3.600492392],"iteration":664,"passed_time":0.9579326787,"remaining_time":0.48256759},
{"learn":[3.597171065],"iteration":665,"passed_time":0.9590558828,"remaining_time":0.4809679653},
{"learn":[3.594358798],"iteration":666,"passed_time":0.9606691362,"remaining_time":0.4796144263},
{"learn":[3.593945251],"iteration":667,"passed_time":0.9628015349,"remaining_time":0.4785181281},
{"learn":[3.593607748],"iteration":668,"passed_time":0.9641371872,"remaining_time":0.4770245276},
{"learn":[3.592238714],"iteration":669,"passed_time":0.9656604526,"remaining_time":0.475623805},
{"learn":[3.590144654],"iteration":670,"passed_time":0.9674161073,"remaining_time":0.4743366607},
{"learn":[3.587151536],"iteration":671,"passed_time":0.9685904324,"remaining_time":0.4727643777},
{"learn":[3.586070865],"iteration":672,"passed_time":0.969835016,"remaining_time":0.4712274149},
{"learn":[3.585102746],"iteration":673,"passed_time":0.971310117,"remaining_time":0.4698028162},
{"learn":[3.584362847],"iteration":674,"passed_time":0.972407732,"remaining_time":0.4681963154},
{"learn":[3.581407561],"iteration":675,"passed_time":0.9735067662,"remaining_time":0.4665920004},
{"learn":[3.57919422],"iteration":676,"passed_time":0.9752840965,"remaining_time":0.4653127964},
{"learn":[3.577632204],"iteration":677,"passed_time":0.977021079,"remaining_time":0.4640129608},
{"learn":[3.573911195],"iteration":678,"passed_time":0.9784194063,"remaining_time":0.462551737},
{"learn":[3.573408216],"iteration":679,"passed_time":0.9795410578,"remaining_time":0.4609604978},
{"learn":[3.571076482],"iteration":680,"passed_time":0.980718341,"remaining_time":0.4593966972},
{"learn":[3.568177107],"iteration":681,"passed_time":0.9819253198,"remaining_time":0.4578478764},
{"learn":[3.564824621],"iteration":682,"passed_time":0.9832045248,"remaining_time":0.4563335788},
{"learn":[3.562475026],"iteration":683,"passed_time":0.9842996235,"remaining_time":0.4547349138},
{"learn":[3.561226889],"iteration":684,"passed_time":0.9854978642,"remaining_time":0.4531851492},
{"learn":[3.559383467],"iteration":685,"passed_time":0.9865905799,"remaining_time":0.451588108},
{"learn":[3.555209766],"iteration":686,"passed_time":0.9877269191,"remaining_time":0.45001241},
{"learn":[3.55345383],"iteration":687,"passed_time":0.9889396719,"remaining_time":0.4484726419},
{"learn":[3.552300968],"iteration":688,"passed_time":0.990714981,"remaining_time":0.447187749},
{"learn":[3.551253986],"iteration":689,"passed_time":0.9920391929,"remaining_time":0.4456987678},
{"learn":[3.549807725],"iteration":690,"passed_time":0.9935488127,"remaining_time":0.4442931739},
{"learn":[3.547992926],"iteration":691,"passed_time":0.9947646286,"remaining_time":0.442756511},
{"learn":[3.545438607],"iteration":692,"passed_time":0.9960740122,"remaining_time":0.4412622248},
{"learn":[3.543313763],"iteration":693,"passed_time":0.9972639053,"remaining_time":0.4397157854},
{"learn":[3.542962896],"iteration":694,"passed_time":0.9984325311,"remaining_time":0.4381610388},
{"learn":[3.539800465],"iteration":695,"passed_time":0.9998444669,"remaining_time":0.4367136752},
{"learn":[3.53953187],"iteration":696,"passed_time":1.001231164,"remaining_time":0.4352554416},
{"learn":[3.536332425],"iteration":697,"passed_time":1.002332517,"remaining_time":0.4336739543},
{"learn":[3.534993327],"iteration":698,"passed_time":1.004033039,"remaining_time":0.4323518522},
{"learn":[3.531637011],"iteration":699,"passed_time":1.007397707,"remaining_time":0.4317418744},
{"learn":[3.531040284],"iteration":700,"passed_time":1.008635511,"remaining_time":0.4302168584},
{"learn":[3.529973872],"iteration":701,"passed_time":1.009703191,"remaining_time":0.428620443},
{"learn":[3.527325183],"iteration":702,"passed_time":1.01071627,"remaining_time":0.4270024641},
{"learn":[3.527200815],"iteration":703,"passed_time":1.011739173,"remaining_time":0.4253903342},
{"learn":[3.523459911],"iteration":704,"passed_time":1.01312478,"remaining_time":0.4239316453},
{"learn":[3.522729934],"iteration":705,"passed_time":1.014233035,"remaining_time":0.4223576662},
{"learn":[3.522260582],"iteration":706,"passed_time":1.016406952,"remaining_time":0.4212266434},
{"learn":[3.518641591],"iteration":707,"passed_time":1.017743115,"remaining_time":0.4197471606},
{"learn":[3.516856405],"iteration":708,"passed_time":1.019690823,"remaining_time":0.4185190825},
{"learn":[3.515083413],"iteration":709,"passed_time":1.022737808,"remaining_time":0.4177379781},
{"learn":[3.514671214],"iteration":710,"passed_time":1.023974394,"remaining_time":0.4162146269},
{"learn":[3.512617621],"iteration":711,"passed_time":1.025133112,"remaining_time":0.4146605848},
{"learn":[3.510747971],"iteration":712,"passed_time":1.026882453,"remaining_time":0.4133453913},
{"learn":[3.508149266],"iteration":713,"passed_time":1.027956506,"remaining_time":0.4117584884},
{"learn":[3.504557165],"iteration":714,"passed_time":1.02923964,"remaining_time":0.4102563599},
{"learn":[3.501367208],"iteration":715,"passed_time":1.030408505,"remaining_time":0.4087095189},
{"learn":[3.497593362],"iteration":716,"passed_time":1.031548893,"remaining_time":0.4071524921},
{"learn":[3.496291169],"iteration":717,"passed_time":1.032616793,"remaining_time":0.4055681555},
{"learn":[3.49330374],"iteration":718,"passed_time":1.034454856,"remaining_time":0.4042862511},
{"learn":[3.490044385],"iteration":719,"passed_time":1.03590713,"remaining_time":0.4028527728},
{"learn":[3.488891789],"iteration":720,"passed_time":1.037415124,"remaining_time":0.401440804},
{"learn":[3.486869081],"iteration":721,"passed_time":1.03851387,"remaining_time":0.3998709916},
{"learn":[3.486303638],"iteration":722,"passed_time":1.039584625,"remaining_time":0.3982917581},
{"learn":[3.486035862],"iteration":723,"passed_time":1.040730703,"remaining_time":0.3967426439},
{"learn":[3.482668951],"iteration":724,"passed_time":1.042213853,"remaining_time":0.3953224959},
{"learn":[3.47820549],"iteration":725,"passed_time":1.043452875,"remaining_time":0.3938100381},
{"learn":[3.474392283],"iteration":726,"passed_time":1.044467786,"remaining_time":0.3922141753},
{"learn":[3.472268163],"iteration":727,"passed_time":1.04569861,"remaining_time":0.3907005797},
{"learn":[3.471209164],"iteration":728,"passed_time":1.046794237,"remaining_time":0.3891375008},
{"learn":[3.470049971],"iteration":729,"passed_time":1.047985315,"remaining_time":0.387611007},
{"learn":[3.469078654],"iteration":730,"passed_time":1.049735868,"remaining_time":0.3862913113},
{"learn":[3.468643292],"iteration":731,"passed_time":1.050958293,"remaining_time":0.3847770801},
{"learn":[3.468134848],"iteration":732,"passed_time":1.052186351,"remaining_time":0.3832656969},
{"learn":[3.467820182],"iteration":733,"passed_time":1.053350682,"remaining_time":0.3817319911},
{"learn":[3.465776156],"iteration":734,"passed_time":1.054443312,"remaining_time":0.3801734388},
{"learn":[3.463037608],"iteration":735,"passed_time":1.055525194,"remaining_time":0.3786122978},
{"learn":[3.45965637],"iteration":736,"passed_time":1.056504382,"remaining_time":0.3770158106},
{"learn":[3.457275091],"iteration":737,"passed_time":1.057813766,"remaining_time":0.3755382204},
{"learn":[3.455522955],"iteration":738,"passed_time":1.058934565,"remaining_time":0.373994481},
{"learn":[3.451270508],"iteration":739,"passed_time":1.05997714,"remaining_time":0.3724244005},
{"learn":[3.450978947],"iteration":740,"passed_time":1.061031721,"remaining_time":0.3708599402},
{"learn":[3.450608492],"iteration":741,"passed_time":1.062196093,"remaining_time":0.3693350298},
{"learn":[3.448122004],"iteration":742,"passed_time":1.063397445,"remaining_time":0.3678238807},
{"learn":[3.445646714],"iteration":743,"passed_time":1.065004736,"remaining_time":0.3664532424},
{"learn":[3.44411263],"iteration":744,"passed_time":1.066260742,"remaining_time":0.3649617307},
{"learn":[3.443264164],"iteration":745,"passed_time":1.067517036,"remaining_time":0.3634709478},
{"learn":[3.439521363],"iteration":746,"passed_time":1.068595363,"remaining_time":0.3619205177},
{"learn":[3.436809225],"iteration":747,"passed_time":1.069688622,"remaining_time":0.3603763806},
{"learn":[3.435509465],"iteration":748,"passed_time":1.071409866,"remaining_time":0.3590438937},
{"learn":[3.434450277],"iteration":749,"passed_time":1.072905129,"remaining_time":0.357635043},
{"learn":[3.431786753],"iteration":750,"passed_time":1.073934433,"remaining_time":0.3560714697},
{"learn":[3.430150302],"iteration":751,"passed_time":1.075012837,"remaining_time":0.35452551},
{"learn":[3.42696281],"iteration":752,"passed_time":1.076173785,"remaining_time":0.3530078683},
{"learn":[3.426870334],"iteration":753,"passed_time":1.078097139,"remaining_time":0.3517399153},
{"learn":[3.425200309],"iteration":754,"passed_time":1.079905747,"remaining_time":0.3504329908},
{"learn":[3.423383783],"iteration":755,"passed_time":1.081338322,"remaining_time":0.3490033737},
{"learn":[3.422752979],"iteration":756,"passed_time":1.082353767,"remaining_time":0.3474398485},
{"learn":[3.420845924],"iteration":757,"passed_time":1.083384498,"remaining_time":0.3458826496},
{"learn":[3.418917862],"iteration":758,"passed_time":1.084511369,"remaining_time":0.3443573649},
{"learn":[3.417095735],"iteration":759,"passed_time":1.085572094,"remaining_time":0.3428122402},
{"learn":[3.414391848],"iteration":760,"passed_time":1.086605499,"remaining_time":0.3412598084},
{"learn":[3.41426711],"iteration":761,"passed_time":1.087629422,"remaining_time":0.3397057776},
{"learn":[3.411976013],"iteration":762,"passed_time":1.088614599,"remaining_time":0.3381411008},
{"learn":[3.408614844],"iteration":763,"passed_time":1.089878656,"remaining_time":0.3366640876},
{"learn":[3.407906721],"iteration":764,"passed_time":1.090898874,"remaining_time":0.3351127259},
{"learn":[3.407494015],"iteration":765,"passed_time":1.092119561,"remaining_time":0.3336239913},
{"learn":[3.406287128],"iteration":766,"passed_time":1.093229646,"remaining_time":0.3321023565},
{"learn":[3.404600442],"iteration":767,"passed_time":1.095242248,"remaining_time":0.330854429},
{"learn":[3.404012662],"iteration":768,"passed_time":1.096290492,"remaining_time":0.3293148292},
{"learn":[3.400398762],"iteration":769,"passed_time":1.097302091,"remaining_time":0.3277655596},
{"learn":[3.399737714],"iteration":770,"passed_time":1.098354316,"remaining_time":0.3262297514},
{"learn":[3.399185251],"iteration":771,"passed_time":1.099488858,"remaining_time":0.3247195073},
{"learn":[3.397245411],"iteration":772,"passed_time":1.10057492,"remaining_time":0.3231959984},
{"learn":[3.396229831],"iteration":773,"passed_time":1.101875061,"remaining_time":0.3217361289},
{"learn":[3.394002836],"iteration":774,"passed_time":1.103719018,"remaining_time":0.3204345535},
{"learn":[3.389617243],"iteration":775,"passed_time":1.105423413,"remaining_time":0.3190912946},
{"learn":[3.385426488],"iteration":776,"passed_time":1.107048035,"remaining_time":0.3177242108},
{"learn":[3.385072258],"iteration":777,"passed_time":1.109733213,"remaining_time":0.3166590916},
{"learn":[3.383842366],"iteration":778,"passed_time":1.110961188,"remaining_time":0.315176409},
{"learn":[3.380110746],"iteration":779,"passed_time":1.11228159,"remaining_time":0.3137204484},
{"learn":[3.378595218],"iteration":780,"passed_time":1.113496202,"remaining_time":0.3122351707},
{"learn":[3.377371219],"iteration":781,"passed_time":1.114594124,"remaining_time":0.310718055},
{"learn":[3.375814782],"iteration":782,"passed_time":1.116208973,"remaining_time":0.3093452708},
{"learn":[3.374195887],"iteration":783,"passed_time":1.117271078,"remaining_time":0.3078195828},
{"learn":[3.373704309],"iteration":784,"passed_time":1.118314305,"remaining_time":0.3062899051},
{"learn":[3.372971757],"iteration":785,"passed_time":1.119358724,"remaining_time":0.3047617899},
{"learn":[3.371565136],"iteration":786,"passed_time":1.120323368,"remaining_time":0.3032133131},
{"learn":[3.3700309],"iteration":787,"passed_time":1.121409481,"remaining_time":0.3016989973},
{"learn":[3.368186663],"iteration":788,"passed_time":1.122396365,"remaining_time":0.3001592308},
{"learn":[3.366710398],"iteration":789,"passed_time":1.123413017,"remaining_time":0.2986287766},
{"learn":[3.364598042],"iteration":790,"passed_time":1.124944701,"remaining_time":0.2972357049},
{"learn":[3.36348442],"iteration":791,"passed_time":1.126040312,"remaining_time":0.2957277587},
{"learn":[3.362001759],"iteration":792,"passed_time":1.128473626,"remaining_time":0.2945700385},
{"learn":[3.361580401],"iteration":793,"passed_time":1.129613761,"remaining_time":0.2930735955},
{"learn":[3.359543675],"iteration":794,"passed_time":1.13058663,"remaining_time":0.291534917},
{"learn":[3.35766119],"iteration":795,"passed_time":1.131812517,"remaining_time":0.2900625044},
{"learn":[3.354592969],"iteration":796,"passed_time":1.133822214,"remaining_time":0.2887903507},
{"learn":[3.350985986],"iteration":797,"passed_time":1.134864466,"remaining_time":0.2872714562},
{"learn":[3.349589624],"iteration":798,"passed_time":1.135872185,"remaining_time":0.2857450678},
{"learn":[3.349110856],"iteration":799,"passed_time":1.136889555,"remaining_time":0.2842223888},
{"learn":[3.345315441],"iteration":800,"passed_time":1.137866835,"remaining_time":0.2826910115},
{"learn":[3.34397474],"iteration":801,"passed_time":1.138881072,"remaining_time":0.2811701399},
{"learn":[3.343800902],"iteration":802,"passed_time":1.14058648,"remaining_time":0.2798200953},
{"learn":[3.342329465],"iteration":803,"passed_time":1.14172272,"remaining_time":0.2783304144},
{"learn":[3.34220347],"iteration":804,"passed_time":1.142726114,"remaining_time":0.2768094313},
{"learn":[3.341279219],"iteration":805,"passed_time":1.143750792,"remaining_time":0.2752948557},
{"learn":[3.337329521],"iteration":806,"passed_time":1.144895735,"remaining_time":0.2738102563},
{"learn":[3.336708453],"iteration":807,"passed_time":1.146993683,"remaining_time":0.2725529545},
{"learn":[3.333252703],"iteration":808,"passed_time":1.148110856,"remaining_time":0.2710620191},
{"learn":[3.332186769],"iteration":809,"passed_time":1.149146911,"remaining_time":0.2695529792},
{"learn":[3.330594851],"iteration":810,"passed_time":1.150176971,"remaining_time":0.2680437083},
{"learn":[3.327867442],"iteration":811,"passed_time":1.151219676,"remaining_time":0.2665385456},
{"learn":[3.327563111],"iteration":812,"passed_time":1.152589685,"remaining_time":0.2651098046},
{"learn":[3.326308994],"iteration":813,"passed_time":1.154746943,"remaining_time":0.2638610952},
{"learn":[3.326249879],"iteration":814,"passed_time":1.156141043,"remaining_time":0.2624369239},
{"learn":[3.322336238],"iteration":815,"passed_time":1.157169548,"remaining_time":0.2609303884},
{"learn":[3.320491154],"iteration":816,"passed_time":1.158322437,"remaining_time":0.2594528837},
{"learn":[3.320434271],"iteration":817,"passed_time":1.159673728,"remaining_time":0.2580203161},
{"learn":[3.319609638],"iteration":818,"passed_time":1.160808214,"remaining_time":0.2565400326},
{"learn":[3.316182682],"iteration":819,"passed_time":1.161784059,"remaining_time":0.255025769},
{"learn":[3.313126612],"iteration":820,"passed_time":1.162762987,"remaining_time":0.2535134893},
{"learn":[3.311222803],"iteration":821,"passed_time":1.164202678,"remaining_time":0.2521022831},
{"learn":[3.309627335],"iteration":822,"passed_time":1.165917751,"remaining_time":0.2507502333},
{"learn":[3.307974895],"iteration":823,"passed_time":1.166908379,"remaining_time":0.2492425664},
{"learn":[3.307321505],"iteration":824,"passed_time":1.167889473,"remaining_time":0.2477341306},
{"learn":[3.306759087],"iteration":825,"passed_time":1.168986182,"remaining_time":0.2462513266},
{"learn":[3.30484037],"iteration":826,"passed_time":1.170415047,"remaining_time":0.2448389397},
{"learn":[3.30201994],"iteration":827,"passed_time":1.171940437,"remaining_time":0.2434465643},
{"learn":[3.299302297],"iteration":828,"passed_time":1.172922985,"remaining_time":0.2419418943},
{"learn":[3.298132671],"iteration":829,"passed_time":1.173871897,"remaining_time":0.2404315934},
{"learn":[3.296976183],"iteration":830,"passed_time":1.174870218,"remaining_time":0.2389326917},
{"learn":[3.293144745],"iteration":831,"passed_time":1.175891589,"remaining_time":0.2374396477},
{"learn":[3.290284404],"iteration":832,"passed_time":1.176900227,"remaining_time":0.2359451835},
{"learn":[3.288285745],"iteration":833,"passed_time":1.178074978,"remaining_time":0.2344849477},
{"learn":[3.286662667],"iteration":834,"passed_time":1.179120358,"remaining_time":0.2329998313},
{"learn":[3.285692682],"iteration":835,"passed_time":1.180150373,"remaining_time":0.2315127527},
{"learn":[3.284565611],"iteration":836,"passed_time":1.181168524,"remaining_time":0.2300244558},
{"learn":[3.283897383],"iteration":837,"passed_time":1.182177715,"remaining_time":0.2285355487},
{"learn":[3.280712855],"iteration":838,"passed_time":1.183276966,"remaining_time":0.2270650673},
{"learn":[3.280468341],"iteration":839,"passed_time":1.184748984,"remaining_time":0.2256664732},
{"learn":[3.277814895],"iteration":840,"passed_time":1.186318847,"remaining_time":0.2242862029},
{"learn":[3.276316385],"iteration":841,"passed_time":1.187390921,"remaining_time":0.2228120731},
{"learn":[3.27557063],"iteration":842,"passed_time":1.188351149,"remaining_time":0.2213180668},
{"learn":[3.27499628],"iteration":843,"passed_time":1.190157298,"remaining_time":0.2199816807},
{"learn":[3.273569958],"iteration":844,"passed_time":1.191178313,"remaining_time":0.2185001638},
{"learn":[3.269665595],"iteration":845,"passed_time":1.192163058,"remaining_time":0.2170131334},
{"learn":[3.267984685],"iteration":846,"passed_time":1.193202371,"remaining_time":0.2155371461},
{"learn":[3.267702508],"iteration":847,"passed_time":1.19412248,"remaining_time":0.2140408219},
{"learn":[3.266671924],"iteration":848,"passed_time":1.19545012,"remaining_time":0.2126183371},
{"learn":[3.265359825],"iteration":849,"passed_time":1.196691748,"remaining_time":0.2111808966},
{"learn":[3.2618983],"iteration":850,"passed_time":1.197752962,"remaining_time":0.2097123283},
{"learn":[3.260456253],"iteration":851,"passed_time":1.199249291,"remaining_time":0.2083202994},
{"learn":[3.258389147],"iteration":852,"passed_time":1.201292215,"remaining_time":0.2070222223},
{"learn":[3.258108469],"iteration":853,"passed_time":1.202350489,"remaining_time":0.2055540648},
{"learn":[3.256424936],"iteration":854,"passed_time":1.203346531,"remaining_time":0.2040763123},
{"learn":[3.254817983],"iteration":855,"passed_time":1.204376299,"remaining_time":0.2026053586},
{"learn":[3.253898449],"iteration":856,"passed_time":1.205387782,"remaining_time":0.2011323836},
{"learn":[3.253023652],"iteration":857,"passed_time":1.206517031,"remaining_time":0.1996799748},
{"learn":[3.252845542],"iteration":858,"passed_time":1.207413427,"remaining_time":0.1981900969},
{"learn":[3.252316026],"iteration":859,"passed_time":1.208388457,"remaining_time":0.1967143999},
{"learn":[3.24975301],"iteration":860,"passed_time":1.209410378,"remaining_time":0.1952474362},
{"learn":[3.249151075],"iteration":861,"passed_time":1.210701285,"remaining_time":0.1938245677},
{"learn":[3.246257135],"iteration":862,"passed_time":1.211848281,"remaining_time":0.1923791593},
{"learn":[3.243826471],"iteration":863,"passed_time":1.213329289,"remaining_time":0.1909870178},
{"learn":[3.243190653],"iteration":864,"passed_time":1.21514729,"remaining_time":0.189647265},
{"learn":[3.24008797],"iteration":865,"passed_time":1.21629183,"remaining_time":0.1882022},
{"learn":[3.240036811],"iteration":866,"passed_time":1.217381222,"remaining_time":0.1867493686},
{"learn":[3.238676314],"iteration":867,"passed_time":1.21846215,"remaining_time":0.1852960873},
{"learn":[3.237848782],"iteration":868,"passed_time":1.219463098,"remaining_time":0.1838316063},
{"learn":[3.236405498],"iteration":869,"passed_time":1.220454862,"remaining_time":0.1823668185},
{"learn":[3.233378068],"iteration":870,"passed_time":1.221435255,"remaining_time":0.1809014328},
{"learn":[3.233169169],"iteration":871,"passed_time":1.222611186,"remaining_time":0.1794658621},
{"learn":[3.232434885],"iteration":872,"passed_time":1.223597272,"remaining_time":0.1780032686},
{"learn":[3.229978115],"iteration":873,"passed_time":1.224638763,"remaining_time":0.176549753},
{"learn":[3.229648848],"iteration":874,"passed_time":1.225763172,"remaining_time":0.1751090245},
{"learn":[3.227208761],"iteration":875,"passed_time":1.226851645,"remaining_time":0.1736639315},
{"learn":[3.226258869],"iteration":876,"passed_time":1.228046184,"remaining_time":0.1722345275},
{"learn":[3.225331995],"iteration":877,"passed_time":1.229837423,"remaining_time":0.1708885713},
{"learn":[3.221968268],"iteration":878,"passed_time":1.231254636,"remaining_time":0.1694901148},
{"learn":[3.221166317],"iteration":879,"passed_time":1.232921564,"remaining_time":0.1681256678},
{"learn":[3.220047503],"iteration":880,"passed_time":1.234183364,"remaining_time":0.1667058119},
{"learn":[3.21982781],"iteration":881,"passed_time":1.235241223,"remaining_time":0.1652590298},
{"learn":[3.216693405],"iteration":882,"passed_time":1.236257299,"remaining_time":0.1638075922},
{"learn":[3.214798761],"iteration":883,"passed_time":1.237230582,"remaining_time":0.1623515244},
{"learn":[3.214395085],"iteration":884,"passed_time":1.238304236,"remaining_time":0.16090959},
{"learn":[3.213470696],"iteration":885,"passed_time":1.239437117,"remaining_time":0.1594761076},
{"learn":[3.211595017],"iteration":886,"passed_time":1.240482742,"remaining_time":0.158032187},
{"learn":[3.210965255],"iteration":887,"passed_time":1.241628919,"remaining_time":0.1566018457},
{"learn":[3.209413583],"iteration":888,"passed_time":1.242651605,"remaining_time":0.1551567246},
{"learn":[3.208331683],"iteration":889,"passed_time":1.243682683,"remaining_time":0.1537135901},
{"learn":[3.207110711],"iteration":890,"passed_time":1.245072384,"remaining_time":0.1523152524},
{"learn":[3.204519413],"iteration":891,"passed_time":1.246298536,"remaining_time":0.1508971321},
{"learn":[3.201421296],"iteration":892,"passed_time":1.247841754,"remaining_time":0.149517433},
{"learn":[3.200691259],"iteration":893,"passed_time":1.249026859,"remaining_time":0.1480949073},
{"learn":[3.200485067],"iteration":894,"passed_time":1.250187785,"remaining_time":0.1466700753},
{"learn":[3.197467568],"iteration":895,"passed_time":1.251492497,"remaining_time":0.145262522},
{"learn":[3.195838544],"iteration":896,"passed_time":1.252676352,"remaining_time":0.1438413202},
{"learn":[3.195671746],"iteration":897,"passed_time":1.253740854,"remaining_time":0.1424070903},
{"learn":[3.194213094],"iteration":898,"passed_time":1.254864262,"remaining_time":0.1409803009},
{"learn":[3.192884691],"iteration":899,"passed_time":1.256279848,"remaining_time":0.1395866497},
{"learn":[3.188364239],"iteration":900,"passed_time":1.257393674,"remaining_time":0.1381597932},
{"learn":[3.185219478],"iteration":901,"passed_time":1.258595914,"remaining_time":0.1367432367},
{"learn":[3.184120387],"iteration":902,"passed_time":1.260272435,"remaining_time":0.1353781021},
{"learn":[3.183725321],"iteration":903,"passed_time":1.261330407,"remaining_time":0.1339465919},
{"learn":[3.181264554],"iteration":904,"passed_time":1.262647072,"remaining_time":0.1325430628},
{"learn":[3.180741589],"iteration":905,"passed_time":1.264091637,"remaining_time":0.1311529954},
{"learn":[3.179782639],"iteration":906,"passed_time":1.265154458,"remaining_time":0.1297236654},
{"learn":[3.176377564],"iteration":907,"passed_time":1.266336717,"remaining_time":0.1283072444},
{"learn":[3.174078182],"iteration":908,"passed_time":1.267431948,"remaining_time":0.1268826262},
{"learn":[3.171242379],"iteration":909,"passed_time":1.268472197,"remaining_time":0.1254532942},
{"learn":[3.170421012],"iteration":910,"passed_time":1.269707218,"remaining_time":0.1240438446},
{"learn":[3.170087224],"iteration":911,"passed_time":1.270968932,"remaining_time":0.1226373531},
{"learn":[3.167303059],"iteration":912,"passed_time":1.271961963,"remaining_time":0.1212055759},
{"learn":[3.16705966],"iteration":913,"passed_time":1.273094287,"remaining_time":0.1197878651},
{"learn":[3.165667683],"iteration":914,"passed_time":1.274616369,"remaining_time":0.1184069851},
{"learn":[3.164689733],"iteration":915,"passed_time":1.275739093,"remaining_time":0.1169891745},
{"learn":[3.163311455],"iteration":916,"passed_time":1.277515761,"remaining_time":0.1156311976},
{"learn":[3.159425016],"iteration":917,"passed_time":1.2786898,"remaining_time":0.1142184789},
{"learn":[3.159327058],"iteration":918,"passed_time":1.279703267,"remaining_time":0.1127921269},
{"learn":[3.15819426],"iteration":919,"passed_time":1.280703897,"remaining_time":0.1113655563},
{"learn":[3.157086603],"iteration":920,"passed_time":1.281701235,"remaining_time":0.1099396282},
{"learn":[3.153354154],"iteration":921,"passed_time":1.282839263,"remaining_time":0.108526532},
{"learn":[3.153261317],"iteration":922,"passed_time":1.284030704,"remaining_time":0.1071184878},
{"learn":[3.153168454],"iteration":923,"passed_time":1.285168511,"remaining_time":0.1057065009},
{"learn":[3.152080399],"iteration":924,"passed_time":1.286138523,"remaining_time":0.1042815019},
{"learn":[3.151635144],"iteration":925,"passed_time":1.287114705,"remaining_time":0.1028579786},
{"learn":[3.147762655],"iteration":926,"passed_time":1.288129931,"remaining_time":0.1014384951},
{"learn":[3.147172317],"iteration":927,"passed_time":1.289536309,"remaining_time":0.1000502309},
{"learn":[3.146254125],"iteration":928,"passed_time":1.290764146,"remaining_time":0.09864828243},
{"learn":[3.144869828],"iteration":929,"passed_time":1.292311442,"remaining_time":0.09727075371},
{"learn":[3.143466218],"iteration":930,"passed_time":1.293446843,"remaining_time":0.09586233313},
{"learn":[3.141919643],"iteration":931,"passed_time":1.294557127,"remaining_time":0.0944526659},
{"learn":[3.141054135],"iteration":932,"passed_time":1.295687707,"remaining_time":0.09304509796},
{"learn":[3.139390417],"iteration":933,"passed_time":1.296900158,"remaining_time":0.09164390835},
{"learn":[3.139025283],"iteration":934,"passed_time":1.297960694,"remaining_time":0.09023256159},
{"learn":[3.137824183],"iteration":935,"passed_time":1.299002967,"remaining_time":0.08882071567},
{"learn":[3.135620453],"iteration":936,"passed_time":1.30008102,"remaining_time":0.08741206431},
{"learn":[3.13443178],"iteration":937,"passed_time":1.301126453,"remaining_time":0.08600196173},
{"learn":[3.132765713],"iteration":938,"passed_time":1.302249768,"remaining_time":0.08459769525},
{"learn":[3.131434124],"iteration":939,"passed_time":1.30337703,"remaining_time":0.0831942785},
{"learn":[3.128384262],"iteration":940,"passed_time":1.304930092,"remaining_time":0.08181814607},
{"learn":[3.128120455],"iteration":941,"passed_time":1.306126001,"remaining_time":0.08041964759},
{"learn":[3.126314615],"iteration":942,"passed_time":1.307325614,"remaining_time":0.07902180273},
{"learn":[3.125409666],"iteration":943,"passed_time":1.308341865,"remaining_time":0.07761350046},
{"learn":[3.123072589],"iteration":944,"passed_time":1.309412749,"remaining_time":0.07620920764},
{"learn":[3.122921099],"iteration":945,"passed_time":1.310423422,"remaining_time":0.07480218267},
{"learn":[3.122182662],"iteration":946,"passed_time":1.311467236,"remaining_time":0.07339784952},
{"learn":[3.120040951],"iteration":947,"passed_time":1.312471296,"remaining_time":0.07199209638},
{"learn":[3.118767799],"iteration":948,"passed_time":1.313737897,"remaining_time":0.07060129899},
{"learn":[3.118203218],"iteration":949,"passed_time":1.315324129,"remaining_time":0.06922758572},
{"learn":[3.116343362],"iteration":950,"passed_time":1.316576935,"remaining_time":0.06783624584},
{"learn":[3.11480829],"iteration":951,"passed_time":1.317812832,"remaining_time":0.06644434449},
{"learn":[3.112607903],"iteration":952,"passed_time":1.319803668,"remaining_time":0.06509000252},
{"learn":[3.111661241],"iteration":953,"passed_time":1.321165913,"remaining_time":0.06370401678},
{"learn":[3.110249676],"iteration":954,"passed_time":1.322903698,"remaining_time":0.06233577634},
{"learn":[3.107333579],"iteration":955,"passed_time":1.32424094,"remaining_time":0.06094832777},
{"learn":[3.107149851],"iteration":956,"passed_time":1.325269079,"remaining_time":0.05954709551},
{"learn":[3.106867336],"iteration":957,"passed_time":1.326513965,"remaining_time":0.05815614462},
{"learn":[3.10364681],"iteration":958,"passed_time":1.327842079,"remaining_time":0.05676905654},
{"learn":[3.102703811],"iteration":959,"passed_time":1.328944768,"remaining_time":0.05537269865},
{"learn":[3.101469264],"iteration":960,"passed_time":1.329993208,"remaining_time":0.05397475036},
{"learn":[3.09863569],"iteration":961,"passed_time":1.330979819,"remaining_time":0.05257508642},
{"learn":[3.09645939],"iteration":962,"passed_time":1.332053912,"remaining_time":0.05117964148},
{"learn":[3.096240186],"iteration":963,"passed_time":1.333127609,"remaining_time":0.04978484846},
{"learn":[3.094838828],"iteration":964,"passed_time":1.334670454,"remaining_time":0.04840773667},
{"learn":[3.094176802],"iteration":965,"passed_time":1.336036177,"remaining_time":0.04702404764},
{"learn":[3.093182279],"iteration":966,"passed_time":1.33758455,"remaining_time":0.0456466289},
{"learn":[3.090150687],"iteration":967,"passed_time":1.338764745,"remaining_time":0.04425668577},
{"learn":[3.088612829],"iteration":968,"passed_time":1.339930767,"remaining_time":0.04286672217},
{"learn":[3.087153684],"iteration":969,"passed_time":1.340948737,"remaining_time":0.04147264134},
{"learn":[3.085866843],"iteration":970,"passed_time":1.34197513,"remaining_time":0.04007958678},
{"learn":[3.082669094],"iteration":971,"passed_time":1.343052078,"remaining_time":0.038688743},
{"learn":[3.081047548],"iteration":972,"passed_time":1.344181873,"remaining_time":0.03730001086},
{"learn":[3.079684322],"iteration":973,"passed_time":1.345206371,"remaining_time":0.03590899963},
{"learn":[3.07613431],"iteration":974,"passed_time":1.346542518,"remaining_time":0.03452673123},
{"learn":[3.074005935],"iteration":975,"passed_time":1.347948373,"remaining_time":0.03314627146},
{"learn":[3.072988853],"iteration":976,"passed_time":1.349471464,"remaining_time":0.03176851961},
{"learn":[3.072344268],"iteration":977,"passed_time":1.350752763,"remaining_time":0.03038503148},
{"learn":[3.070654438],"iteration":978,"passed_time":1.353751753,"remaining_time":0.02903859736},
{"learn":[3.069724506],"iteration":979,"passed_time":1.355334921,"remaining_time":0.02765989635},
{"learn":[3.067763166],"iteration":980,"passed_time":1.356615342,"remaining_time":0.02627491489},
{"learn":[3.066737893],"iteration":981,"passed_time":1.358392332,"remaining_time":0.02489924845},
{"learn":[3.065248174],"iteration":982,"passed_time":1.359469114,"remaining_time":0.02351065608},
{"learn":[3.063186837],"iteration":983,"passed_time":1.360595461,"remaining_time":0.02212350343},
{"learn":[3.062880371],"iteration":984,"passed_time":1.361608002,"remaining_time":0.02073514723},
{"learn":[3.061288645],"iteration":985,"passed_time":1.362634988,"remaining_time":0.01934775845},
{"learn":[3.059970575],"iteration":986,"passed_time":1.363675768,"remaining_time":0.01796128165},
{"learn":[3.059576341],"iteration":987,"passed_time":1.365492484,"remaining_time":0.01658492896},
{"learn":[3.058175919],"iteration":988,"passed_time":1.367155686,"remaining_time":0.01520597831},
{"learn":[3.056830702],"iteration":989,"passed_time":1.368279099,"remaining_time":0.013821001},
{"learn":[3.056336579],"iteration":990,"passed_time":1.36926835,"remaining_time":0.01243533315},
{"learn":[3.055810414],"iteration":991,"passed_time":1.370779552,"remaining_time":0.0110546738},
{"learn":[3.055476518],"iteration":992,"passed_time":1.371807951,"remaining_time":0.009670348092},
{"learn":[3.053331734],"iteration":993,"passed_time":1.372752195,"remaining_time":0.008286230551},
{"learn":[3.050890374],"iteration":994,"passed_time":1.373694159,"remaining_time":0.006902985722},
{"learn":[3.04972623],"iteration":995,"passed_time":1.374730496,"remaining_time":0.005521006006},
{"learn":[3.047217327],"iteration":996,"passed_time":1.375920897,"remaining_time":0.004140183242},
{"learn":[3.047155483],"iteration":997,"passed_time":1.376904446,"remaining_time":0.002759327546},
{"learn":[3.04430671],"iteration":998,"passed_time":1.377980048,"remaining_time":0.001379359408},
{"learn":[3.042664195],"iteration":999,"passed_time":1.379443763,"remaining_time":0}
]}